Workbook

Sheet 他部署受付 - 作業内容管理・進捗
B1: システム運営課 - 作業内容管理・進捗
A3: f | B3: No. | C3: 依頼日 | D3: 依頼部署 | E3: 課題件名 | F3: 課題内容 | G3: 対応内容 | H3: 期限 | I3: 状況 | J3: 備考 | K3: 進捗 | L3: 効果 | M3: 対応者 | N3: 年度
B4: =ROW()-3 -> 1 | C4: 45506 | D4: 商品部 商品管理課 | E4: 楽天カテゴリの取得 | F4: データシートの「楽天商品カテゴリ」が非常に細かく分類されており、特定の商品がどのカテゴリに当てはまるのかを判断するのが非常に困難で時間がかかっています。 | G4: WEBスクレイピングを利用して 既に商品が存在するなら他社で一番使われているカテゴリを取得することで作業の効率化とデータの正確性向上を目指す。 また同時にYahooカテゴリについても取得できるようにしました。 | H4: 45520 | I4: 完了 | K4: 現在はメーカーからのデータシートにカテゴリが入っているものが多く、プログラムはあまり使用されていない状況とのこと。
B5: =ROW()-3 -> 2 | C5: 45527 | D5: マーケティング部 サイト運営課 | E5: b-dash用のデータ作成 週次作業 | F5: 基幹データを抽出してb-dash(販促メール)用に加工する作業が、単純だがファイルサイズが大きいため時間がかかっています。 | G5: 基幹データを抽出する際に、余計なデータを削除し、b-dash用にデータを整える作業を、データファイルを開かずにスムーズに処理・保存できるプログラムを作成しました。 この取り組みにより、作業の効率が向上し、時間の短縮を実現しました。 | H5: 45534 | I5: 完了 | K5: 削減工数：約３時間/月 また、上記の時間削減だけでなく、 Excel上の手処理によるミスを防止できることも大きなメリットとなっているとのこと。
B6: =ROW()-3 -> 3 | C6: 45527 | D6: マーケティング部 サイト運営課 | E6: b-dash用のデータ作成 月次作業 | F6: 基幹データ(直近25か月分)を抽出してb-dash(販促メール)用に取得する行程に時間がかかっています。 | G6: プログラムを作成しデータを自動取得し、利用したい時にデータが準備してある状態にすることで作業効率を高めました。 | H6: 45568 | I6: 完了 | K6: 削減工数：不明
B7: =ROW()-3 -> 4 | C7: 45540 | D7: 商品部 商品管理課 | E7: 短縮商品名の取得 | F7: 商品データシートでは、データベースや納品書印字の制約により、限られた文字数で商品を表現する必要がありました。このため、適切な表現を考え入力する作業が、非常に手間と時間のかかるプロセスとなっていました。この問題は業務全体の効率に影響を及ぼし、現場の負担を大幅に増加させていました。 | G7: ChatGPTのAPIを使って自動で商品名を提案する機能を導入することで手作業が減り、作業時間が短縮されます。結果として、データ入力が効率化され、スタッフの負担が軽くなります。 | I7: 完了 | K7: とりらえず完了！
B8: =ROW()-3 -> 5 | C8: 45547 | D8: 事業管理部 | E8: SQLの作成 受注データ取得用 | F8: DWH用の受注データを作成する工程で、現在は基幹のインプロで複数取得したデータを組わせてデータを作成しているので、作成に時間がかかってしまっている。 | G8: 一度でデータを作成できるようにインプロからSQLに作り直し、直接CSVファイルとして書き出すことで作業負担を減らします。 | I8: 完了 | K8: ベースのSQLは作成済み。 岡村部長と随時チューニング中です。
B9: =ROW()-3 -> 6 | C9: 45555 | D9: 商品部 商品管理課 | E9: 売価データの統合 | F9: 売価データ、契約単価の更新に伴い、大量のエクセルファイル(毎月およそ250ファイル)を1つにまとめる作業が発生していました。この作業は現在すべて手作業で行われており、作業に時間がかかっていました。 | G9: プログラムを作成し、この作業を完全自動化しました。 これによりこれまで数時間を費やしていた作業がわずか数秒で完了するようになりました。 | H9: 45555 | I9: 完了 | K9: 削減工数：約3時間→約4分 作業時間の98.8%削減。
B10: =ROW()-3 -> 7 | C10: 45567 | D10: マーケティング部 サイト運営課 | E10: プライスサーチの自社ツール化 | F10: 楽天とヤフーでの価格調査に利用していた「プライスサーチ」が、2024年9月から調査可能な件数に制限(8日間内で7.5万点まで)がかかり、価格調査にかかる日数が2倍になり、調査件数も半減しました。このためリアルタイムの価格を取得できず、他店の価格追跡や価格調整の精度が低下しています。 現在は9.8万円/月(税抜) 現在は価格調査する商品を厳選して対応中。 | G10: 自社で価格を調査するプログラムを開発し、商品価格データを収集します。 | H10: 2025/7末 | I10: 完了 | K10: 楽天約55万件、ヤフー約53万件の価格調査データを1日で取得し、自動的にNASサーバーに保存できるツールを実装。 楽天は稼働開始から2か月、ヤフーは１か月が経過しましたが、現在までに大きな問題は発生していません。 今後も取得データの確認は継続しますが、ツールとしての実装は完了としています。
B11: =ROW()-3 -> 8 | C11: 45573 | D11: 顧客部サービス課 | E11: インプロ出力ファイルの破損 | F11: インプロで出力したエクセルファイルが開けるときと開けない場合がある。開けない場合はやり直さないといけないので無駄な作業になっている。 | G11: プログラムを作成し、別ルートで同じ結果のファイルを出力するようにしました。 | H11: 45573 | I11: 完了 | K11: 根本的な解決にはなっていないので、引き続き調査してみます。
B12: =ROW()-3 -> 9 | C12: 45594 | D12: 顧客部 顧客課 | E12: 買い物コネクトの欠品対応ツールの自動化 | F12: 買い物コネクトにおける現在の業務を簡略化したい。 【現在の流れ】 ・インプロで買い物コネクトの欠品情報を取得しそれをエクセル化 →手動で注文日ごと、施設ごとに並び替え →表示されている伝票番号をSCAWの受注画面で一つ一つ入力し、 欠品している商品の入荷日を調べ、お客様へ案内する | G12: エクセルで全ての情報を一括で取得できるようにしました。 | H12: 45597 | I12: 完了 | K12: データの作成に３０分かかっていたのが約１０秒で完了できるようになりました。 作業時間は 約99.44% 削減。
B13: =ROW()-3 -> 10 | C13: 45597 | D13: 顧客部 サービス課 | E13: 基幹⇔OA間のデータ移動 | F13: 研修を通じ基幹とOA間でのデータの移行作業に時間が取られていると感じました。 | G13: 基幹ネットワークとOAネットワークを行き来できる端末を作成し、 フォルダを監視し、そのフォルダに入ったものを移動するプログラムを作成することにより、基幹⇔OA間のデータ移行をスムーズにできるようになります。 セキュリティの為、該当の端末とOA側にはウィルス対策をし、ユーザーは限定し、移動ファイルのログは残すようにします。 | H13: ー | I13: 完了 | K13: 同時接続数の問題で中継端末を端末→サーバーに変更。 現在テスト運用中。 問題なければ２月に正式運用したい。 ※USB端末管理台帳をどうするか
B14: =ROW()-3 -> 11 | C14: 45618 | D14: 顧客部 サービス課 | E14: 買い物コネクト 伝票の対象化と出荷指示解除のツール化 | F14: 買い物コネクトの伝票の対象化と出荷指示解除の作業が平日毎日あり、 確認することも多く通常のObjectBrowserを使った方法だと厳しい。 | G14: 福岡システムにツール化してもらいました。 | H14: ー | I14: 完了 | K14: ツールの運用を顧客部に譲渡済み。
B15: =ROW()-3 -> 12 | C15: 45617 | D15: 営業部 | E15: BtoBの価格調査 | F15: アスクル、たのめーる、カウネット、モノタロウなど 営業で他社サイトの商品をForestで買ったらいくらになるかの調査に 現在のところ、マンパワーで作業していてかなり時間がかかっているので 改善できるなら改善したい、とのこと。 | G15: 楽天やヤフーのプライスサーチのロジックを使って、BtoBのサイトから欲しい情報を抽出します。 | I15: 完了 | K15: まずはアスクルのデータ取得を行い、42,000件の調査が完了しました。 人の手で1行の調査に約30秒かかるところが1秒で終わりました。 作業時間は 約96.67% 削減。 いったん完了。
B16: =ROW()-3 -> 13 | C16: 45617 | D16: 物流部 | E16: 倉庫レイアウトの データ作成自動化 | F16: 現在、毎朝インプロでデータを抽出してそれをCSVに変換(約３０分前後)し、そのデータをもとに倉庫レイアウト修正作業をしている。 自動化が実現できると業務がスムーズになるので対応をお願いしたい、とのこと。 | G16: インプロと同じ結果になるSQLを作成しsqlplusのスプール機能を使って 直接CSVに出力し、それをバッチファイルにしてスケジューリングすることで 自動化が実現できると考えます。 | H16: 45628 | I16: 完了 | K16: ツール（インプロ）が７個あり、全部対応完了。 今までのインプロでの作業でもデータ取得まで待機しているわけではなく、他の作業を並行して行っていたため、効率の向上を数値で表現するのは難しいですが、自動化により、作業を開始する前にデータがすでに準備されている状態になり、全体の流れがスムーズになりました、とのこと。
B17: =ROW()-3 -> 14 | C17: 45621 | D17: 物流部 川口配送センター | E17: コピー用紙配送の 一般貨物管理表の作成 | F17: 新しい一般貨物配送業務「コピー用紙配送」ができたが、 荷主と下請けの請求金額を精査する管理表が欲しい。 | G17: 適切なエクセルの計算式を入力するだけです。 | H17: 45629 | I17: 完了 | K17: 荷主への請求額、 各業者への支払額が一目でわかるようにしました。
B18: =ROW()-3 -> 15 | C18: 45625 | D18: マーケティング部 サイト運営課 | E18: 楽天の商品更新csv | F18: イベント期間中に全商品に対し商品名を更新しているが、 商品数が多い（約50万点強）ため元となるexcelを作成し、1つのcsvに対し商品数5万点までのため、そこから計11個のcsvへ手作業で分けているので作業を簡略化したい。 | G18: プログラムで自動化します。 | H18: 45630 | I18: 完了 | K18: 手作業だと１０分？かかっていたのが約15秒で終わるようになりました。 作業時間は約 97.5% 削減。
B19: =ROW()-3 -> 16 | C19: 45625 | D19: マーケティング部 サイト運営課 | E19: EDION連携納期回答【花王】の 応答速度の改善 | F19: SCAWメニューの「EDION連携納期回答【花王】」の 応答速度が15:30ぐらいから開始しても17:30以降になるぐらい遅い。 また動作中はSCAW業務が行えない。 （現在はリモートで１台SCAW端末を利用して対応しているとのこと） | G19: メニューでどのSQLが呼ばれているか調査して、 必要であればSQLを改修してみます。 また他の方法でデータを取得することができればSCAW業務は行えるので、合わせて調査してみます。 | H19: ー | I19: 完了 | K19: 下村さんにシステム内で使われているSQLの見直しを して修正していただきました。 今まで1時間かかっていたところが、2秒程度で終わるようになったそうです。 1時間が2秒で終わる削減効果は99.94%になります。
B20: =ROW()-3 -> 17 | C20: 45627 | D20: 商品部 商品一課 | E20: 未引き当てメールの題名変更 | F20: 理由は各MDが自分の担当の商品が欠品していることを確認するために、欠品のメールの題名に大分類コードを入れられるか、確認してほしい。 | G20: 簡単にできるか、福岡に確認。 | H20: ー | I20: 完了 | K20: 簡単にはできないそう。 福岡対応予定。 2/13 完了
B21: =ROW()-3 -> 18 | C21: 45631 | D21: 商品部 商品二課 | E21: 売価の設定方法について | F21: セールなどで期間限定で売価を変更するが、変更中に他の売価を変更すると 元の売価がわからなくなってしまう。 | G21: 現在の運用を調査して、対応。 | H21: ー | I21: 完了 | K21: 福岡システムで対応予定。
B22: =ROW()-3 -> 19 | C22: 45638 | D22: 商品部 商品一課 | E22: MDの日時作業 | F22: MDが毎日自分の担当商品の前日の売上データを、岡村さんが作成してくれたLookerStudioから取得してエクセルに入力している。10分ぐらいで終わるが、毎日の作業なので簡略化出来るならやってほしい。 | G22: SCAWデータを使って作成しているので、簡単に取れないか調査してみる。 | H22: ー | I22: 完了 | K22: データを見る
B23: =ROW()-3 -> 20 | C23: 45638 | D23: 管理部 管理課 | E23: 値引伝票自動作成 | F23: 値引伝票を作成するためのデータ作成業務で 月に約３時間ほどの工数で手動で作業しているものを、 ミスもあるので自動作成するようにしてほしい。 | G23: 今までSQLで抽出したデータを加工していたものをSQL内で自動計算して結果を出力することで工数を減らせないか検討中です。 | H23: ー | I23: 完了 | K23: 完了済み。 しばらくは今までの作業でやっていただき、 ツールと比べて整合性のチェックをしてもらっています。
B24: =ROW()-3 -> 21 | C24: 45639 | D24: 顧客部 顧客課 | E24: 重要メモ抽出ツールの改修 | F24: 重要メモ抽出ツールで、お客様から問い合わせがあった際に色々調べなくて済むように、表示内容を追加したい。 | G24: インプロを修正します。 | H24: ー | I24: 完了 | K24: 完了済み。 30分/日ぐらい短縮できているとのこと。
B25: =ROW()-3 -> 22 | C25: 45645 | D25: 商品部 商品一課 | E25: 楽天の価格調査 | F25: 各MDが自分の商材リストの最新の楽天価格を調査する際、 WEBを回覧すると時間がかかるのでツール化してほしい。 | G25: マーケティング部で使う予定のプライスサーチをカスタマイズしてＭＤさんが使いやすいように改良します。 | H25: ー | I25: 完了 | K25: 完了済み。 箱バラ等が取れるように別途チューニング中。
B26: =ROW()-3 -> 23 | C26: 45646 | D26: マーケティング部 販売促進課 | E26: b→dashのSFTP自動連携 | F26: 「新規入会後から７日経ったお客様にクーポンメールを送信する」等を自動でやりたいが、現状できていない。 B-dashのデータ自動登録機能をうまく利用して販促に繋げたい。 | G26: SFTPでB-Dashのサーバーにアップロードすると自動的に登録できる機能があるので、それとNASの基幹→OAへのデータ移動をうまく連携させて自動化できるようにする。 | H26: 2025/2末 | I26: 完了 | K26: 希望は２月末まで。 自動アップロード作成＋テスト済み。 1/23(木)の朝に本番。
B27: =ROW()-3 -> 24 | C27: 45652 | D27: システム部 | E27: Google Play Console デベロッパー アカウント | F27: 配送支援アプリをGoogle Playにあげているが、 デベロッパーアカウントの設定が必要になっており、対応しないと「デベロッパープロフィールとアプリが削除される」と注意表示されている。 | G27: 調査中 | H27: 45756 | I27: 完了 | K27: 調査中です。
B28: =ROW()-3 -> 25 | C28: 45663 | D28: システム部 | E28: 基幹メールアドレスの枯渇 | F28: 現在基幹メールアドレスが枯渇していて、新規で作れない状態になっている。 | G28: メールサーバーのソフトウェアを入れ替えて対応。 | H28: 2025/2末 | I28: 完了 | K28: ※古いメールはサーバー上から削除されます。 PCで受信したメールはそのまま残ります。 長期間使っていないメールは受信しておいてください。 移行する日程が決まりましたらまたご連絡します。
B29: =ROW()-3 -> 26 | C29: 45672 | D29: 商品管理課 | E29: アスクルデータ情報の取得 | F29: 現在アスクルデータの取得をオクトパスという無料ソフトを使って取得しているが、１度に２万件、月に５万件の制限がある。 有料版なら無制限 ＄９９/月 | G29: 自社で作成することで、 無制限で同じデータを取得可能。 | H29: 45691 | I29: 完了 | K29: 作成済み。 4万件のデータ取得で問題なく完了。
B30: =ROW()-3 -> 27 | C30: 45677 | D30: 商品管理課 | E30: カタログの文字校正 | F30: カタログの規約(PDF)が、規約文書(Word)と差異がないか調査してもらいたい。 | G30: PDFとWordをテキスト化して、プログラムで精査する。 | H30: 45680 | I30: 完了 | K30: 完了済み。
B31: =ROW()-3 -> 28 | C31: 45691 | D31: 商品部 商品一課 | E31: 楽天の価格調査（箱バラ） | F31: 以前に作った楽天の価格調査だとJANコードで商品を検索して価格を取得するが、たとえば「６本入り」のデータがとれない。 | G31: 再検索機能を追加して、売価に対して明らかに おかしい結果のものは商品名と価格を絞って検索して目的の情報を取れるようにする。 | H31: - | I31: 完了 | K31: 2/15完了。
B32: =ROW()-3 -> 29 | C32: 45693 | D32: 商品部 商品一課 | E32: カウネットの売価データ取得 | F32: カウネットの価格調査を自動化したい | G32: 自動化プログラムを開発し、商品価格データを収集します。 | H32: - | I32: 完了 | K32: 完了済み。
B33: =ROW()-3 -> 30 | C33: 45693 | D33: マーケティング部 販売促進課 | E33: b→dashのSFTP自動連携 (伝票データ) | F33: 伝票データも顧客データと同じように自動連係したい | G33: B-Dashへのアップロードするプログラムは汎用性を持たせているので顧客データと同じように伝票データ作成プログラムを作成して対応します。 | H33: 45696 | I33: 完了 | K33: 2/19完了。
B34: =ROW()-3 -> 31 | C34: 45694 | D34: 物流部 川口配送センター | E34: 請求書確認の修正 | F34: コピー機配送請求書の精査で、「コース」も見るようにしたい。 | G34: ピボットテーブルの項目を追加します。 | H34: - | I34: 完了 | K34: 完了済み。
B35: =ROW()-3 -> 32 | C35: 45693 | D35: 商品管理課 | E35: アスクルPB品のデータ取得 | F35: アスクルのPB品にしぼった情報取得がしたい。 | G35: 巡回プログラムを作成して情報を取得します。 | I35: 完了 | K35: No39で対応します。
B36: =ROW()-3 -> 33 | C36: 45700 | D36: 商品部 | E36: カインズホームの情報取得 | F36: 当社の扱いにないが多くのお客様が欲しいと思う 商品(塊＝群)を探し出して品揃え強化を図りたいので カインズホームの商品情報を取得したい。 | G36: プログラムを作成して自動取得します。 | H36: 45703 | I36: 完了 | K36: 2/13に完了済み。
B37: =ROW()-3 -> 34 | C37: 45702 | D37: 商品部 | E37: DCMの情報取得 | F37: カインズホームのデータだとJAN情報がないものが多く 自社と付け合わせが難しいのでDCMの情報で取得して欲しい。 | G37: プログラムを作成して自動取得します。 | H37: 45703 | I37: 完了 | K37: 2/14に完了済み。
B38: =ROW()-3 -> 35 | C38: 45707 | D38: 商品部 | E38: カウネットの情報取得 | F38: DCMと同じように「たのめーる」での全データ情報が欲しい。 | G38: プログラムを作成して自動取得します。 | H38: - | I38: 完了 | K38: 一応今は不要とのことでとりあえず完了にしてます。 必要になったら再申請してください。
B39: =ROW()-3 -> 36 | C39: 45707 | D39: 商品部 | E39: たのめーるの情報取得 | F39: DCMと同じように「たのめーる」での全データ情報が欲しい。 | G39: プログラムを作成して自動取得します。 | H39: - | I39: 完了 | K39: No.51で完了済み。
B40: =ROW()-3 -> 37 | C40: 45707 | D40: 商品部 | E40: アスクルの情報取得 | F40: DCMと同じようにカウネットでの全データ情報が欲しい。 | G40: プログラムを作成して自動取得します。 | I40: 完了 | K40: No39で対応。
B41: =ROW()-3 -> 38 | C41: 45708 | D41: 営業部 | E41: アスクルの申込番号に対する 自社商品データ取得 | F41: 営業で利用したいので、エクセルにあるアスクルの申込番号の現在価格とフォーレストの価格を調査してほしい。 | G41: プログラムを作成して自動取得します。 | I41: 完了 | K41: 2/21に完了済み。
B42: =ROW()-3 -> 39 | C42: 45714 | D42: 商品部 | E42: アスクルのエレコム商品 情報取得 | F42: アスクルのエレコム商品の品揃えと弊社の揃えを比較したい | G42: プログラムを作成して自動取得します。 | I42: 完了 | K42: メーカー名、カテゴリで検索可能。 3/5に完了済み。
B43: =ROW()-3 -> 40 | C43: 45723 | D43: 商品部 | E43: エディオンの売価情報取得 | F43: うちで売ってる商品が、エディオンでいくらで売られているか調査したい。 | G43: プログラムを作成して自動取得します。 | I43: 完了 | K43: 3/8に完了済み。
B44: =ROW()-3 -> 41 | C44: 45726 | D44: 商品部 | E44: 株式会社ファースト データシート作成の効率化 | F44: ２６万行のデータシートの作成を急ぎたい。 | G44: エクセルではなく、違う方法を利用して効率的に進める方法を考えます。 | H44: 45747 | I44: 完了 | K44: 他にも、現場レベルでのデータシート作成に関連する作業を効率化するためのツールを複数作成しました。 6/13に完了済み。
B45: =ROW()-3 -> 42 | C45: 45750 | D45: 商品部 | E45: 売上データの取得 | F45: 24年度の商品売上ランキング上位１万アイテムと、それに付随する楽天価格、アスクル価格を調査したい。 | G45: SCAWでデータを取得して、楽天、アスクル価格は既存のツールでデータ取得します。 | H45: - | I45: 完了 | K45: 今後は商品部で作成出来るようにSCAWのデータ取得SQLを作成。 | L45: 手作業（1アイテム1分）と仮定した場合、アスクル、楽天で１万アイテムの検索に約20,000分（約334時間）のみなし削減。 | N45: 25
B46: =ROW()-3 -> 43 | C46: 45757 | D46: 商品部 | E46: カテゴリの取得 | F46: 他社サイト（アスクル、ロハコ、姫路流通センター）のカテゴリ構造を取得してほしい。 | G46: プログラムで解析してカテゴリデータを取得します。 | H46: 45765 | I46: 完了 | K46: 4/16に完了済み。 | L46: 手作業で3サイトの全カテゴリ階層（約1万件規模）を調査・転記したと仮定した場合、約75〜100時間のみなし削減。 | N46: 25
B47: =ROW()-3 -> 44 | C47: 45737 | D47: 顧客部 サービス課 | E47: おせち・母の日など問番マクロの修正 | F47: 2025年度も母の日ギフトが実施されるが、運用の追加や修正があるため、 サービス課（直送担当）利用分の「問番マクロ」を調整・修正を希望。 | G47: VBAマクロを修正します。 | H47: 45786 | I47: 完了 | K47: 4/17に完了。 細かい修正をして5/9に完了済み。 | L47: 新規運用へのシステム対応。既存自動化ツールの延命・アップデートにより、 現場の継続的な業務効率化（工数削減効果）を維持。 | N47: 25
B48: =ROW()-3 -> 45 | C48: 45764 | D48: 商品部 | E48: データシートの効率化(家具) | F48: 家具のデータシート作成を簡略化したい。 | G48: ファーストのデータシート作成プログラムを改変して家具用に調整します。 ・「詳しく見る」を「品番、カラー、その他」の記述にする ・「商品名」を椅子の場合は「メーカー名/商品名 背【色】/座【色】【キャスター素材】キャスター」、テーブルの場合は「メーカー名/商品名/天板カラー/天板Ｗ/天板Ｄ」にする ・キーワードを「/」で区切る ・対照表から必要な画像を抽出して自動でリサイズ・リネーム | H48: - | I48: 完了 | K48: １データシートが約3日かかるものが約2時間で終わります。 作業時間を約９２％軽減。 現場で使えるようにEXE化してツール化。 | L48: 1データシート（メーカーのカタログ更新データ一式等）あたり、 約3日（約24時間）かかっていた作業が約2時間に短縮し、 １データシートにつき約22時間の工数を削減（約92%減）。 今回の３データシートあり、年に２回の改定があったとして 年間約132時間の実工数削減。 | N48: 25
B49: =ROW()-3 -> 46 | C49: 45765 | D49: 川口配送センター | E49: エディオン引越サービスの料金改定による料金シートの作成 | F49: エディオン引っ越しサービスの料金が５月に改訂されるので、それに伴って受付表のデータを更新したい。 | G49: エクセルデータを修正します。 | H49: 45777 | I49: 完了 | K49: 4/19に完了済み。 | L49: 外部サービスの料金改定に伴うシステム対応。 既存ツール（受付表）をアップデートすることで手計算への逆戻りを防ぎ、 現場の継続的な業務効率化を維持。 | N49: 25
B50: =ROW()-3 -> 47 | C50: 45771 | D50: 商品部 | E50: 商品ランクの再設定 | F50: 商品ランクを設定しなおしたい。 | G50: S,A,Kランクについてはエクセルデータを元にランクを再設定、 Zランクについては廃盤設定のものを更新、 PランクはForest,Goono,e angleのものを設定するプログラムを作成。 | I50: 完了 | K50: 5/12に更新済み。 頻繁に更新する場合はプログラムをEXE化して商品部に引継ぎ予定。 | L50: 従来は期実施できていなかった、約3万件の商品ランク（S,A,K,Z,P等）の再設定・更新をプログラム化。 もし手作業で行えば週に数時間（年間約100〜150時間）かかる規模のデータメンテナンスを自動化し、商品ランクの鮮度と正確性を常に維持できる新たな運用を確立（みなし削減・新規価値創出）。 | N50: 25
B51: =ROW()-3 -> 48 | C51: 45777 | D51: 商品部 | E51: EDIONドロップシッピング 家電商品検索 | F51: ドロップシッピング一覧から家電を抜き出したい。 | G51: ドロップシッピング一覧のエクセルをデータフレーム化して検索します。 | H51: 45777 | I51: 完了 | K51: 4/30に完了済み。 | N51: 25
B52: =ROW()-3 -> 49 | C52: 45779 | D52: 顧客部 顧客課 | E52: ライフル買い物コネクト 欠品商品表示ツールの修正 | F52: 運用上の改善のため、表示方法を修正してほしい。 ①SCAW受注日の日付が変わる境目に、下線の太線を追加 ②入荷予定数量、現在在庫数～発注日付、メアドの表示削除 ③伝票に品目が複数ある場合、分納伝票列に「複」を表示 ④入荷予定日が翌々営業日の場合、出荷依頼列に「★」を表示 | G52: VBAマクロを修正します。 | H52: - | I52: 完了 | K52: 5/12に完了済み。 これまで平均約4分かかっていた処理が、約1.5分に短縮され、約60～70％の工数削減になった。 また今回の改修により確認漏れの防止に加え、業務負担の軽減も実感できているとのこと。 | N52: 25
B53: =ROW()-3 -> 50 | C53: 45779 | D53: 川口配送センター | E53: 運行管理システムの データ修正 | F53: 運行管理をアプリで記録しているが、データの打ち漏れがある部分を修正したい。 | G53: 依頼のエクセルデータでDBを更新します。 | H53: 45787 | I53: 完了 | K53: 5/6に完了済み。 | N53: 25
B54: =ROW()-3 -> 51 | C54: 45813 | D54: 商品部 商品課 | E54: 「たのめーる」価格調査 | F54: 「たのめーる」の価格を一括で調査したい。 | G54: プログラムを作成してデータ取得します。 | H54: - | I54: 完了 | K54: 6/12に完了済み。 | N54: 25
B55: =ROW()-3 -> 52 | C55: 45819 | D55: 顧客部 顧客課 | E55: 注文取込業務の処理漏れ防止 | F55: 外部サイトのデータ取込漏れが発生。 作業チェックシートを作成して複数人でダブルチェックをしているが、お客様から「商品が届かない」との問い合わせを受け、初めて問題を認識。 過去にも同様の漏れが複数回発生しており、効果的な防止策がないまま対応が続いている。 | G55: SCAWへのデータ取込有無を自動で確認できるツールを作成し、ヒューマンエラーの根本的な解消を図る。 | H55: - | I55: 完了 | K55: 基幹側でエクセルマクロとSQLを利用して１ボタンでデータの取り込み情報を確認できるツールを作成しました。 6/16に完了済み。 その後取り込み漏れはゼロになったとのこと。 | N55: 25
B56: =ROW()-3 -> 53 | C56: 45819 | D56: 川口配送センター | E56: 運行管理システムのデータ修正 | F56: 運行管理をアプリで記録しているが、データの打ち漏れがある部分を修正したい。 | G56: 依頼のエクセルデータでDBを更新します。 | H56: - | I56: 完了 | K56: 6/16に完了済み。 以前にもデータ修正依頼があったので、 今後は川口配送センターで管理・修正できるような仕組みを作成しました。 | N56: 25
B57: =ROW()-3 -> 54 | C57: 45820 | D57: 管理部 経理課 | E57: 滞留在庫抽出ツール作成 | F57: 現行のツールの問題点 1.現行の作業工程が複雑で作業工数がかかる・・・[4H～8H]×2人×2回/年(在庫管理課でも別途情報取得の工数発生)。 2.現行の作業工程が複雑で特定の人間しか作業できない。 3.ｱｸｾｽ内で連結したﾃﾞｰﾀを抽出、ﾀﾞｳﾝﾛｰﾄﾞしようとするとｴﾗｰが発生することが頻発し作業自体がｽﾑｰｽに実施できない。 4.在庫管理課でも別方法で滞留在庫を監視しているが、経理課で把握する滞留在庫と一致しない。 | G57: 他の方法を利用して結果が一緒になるようにします。 | H57: 7月末 | I57: 完了 | K57: 6/25に完了済み。 経理課で今までの作業の結果と新ツールの結果が一致することを確認済み。 従来最大16人時かかっていた作業をツール化により約99.7%削減し、 3分で完了できるようにしました。 | N57: 25
B58: =ROW()-3 -> 55 | C58: 45828 | D58: 営業管理部 商品管理課 | E58: 改廃データの運用 | F58: 改廃のデータ入力にエクセルを使っているが、 行数が８０万件以上になっていて重すぎて作業に時間がかかる。 改善できるならして欲しい。 | G58: データはDB化、入出力はWEBアプリケーションを構築して 効率をあげれるようにする。 | H58: - | I58: 完了 | K58: 11/7(金)：処理データのアップロードも非同期化の希望 → 対応済み→検証待ち 2月より正式運用 運用してみて追加改修があれば対応します。 | L58: 現段階で作業の4割減とのこと | N58: 25
B59: =ROW()-3 -> 56 | C59: 45840 | D59: 商品部 | E59: チルドの分類調査 | F59: チルド食品取扱にあたり、他店の分類調査をして欲しい。 | G59: 依頼されたURLからスクレイピングで分類情報を取得します。 | H59: 急ぎ | I59: 完了 | K59: 7/3に完了済み。 | N59: 25
B60: =ROW()-3 -> 57 | C60: 45840 | D60: 商品部 商品課 | E60: 中山福のデータ変換 | F60: 仕入先「中山福」から送られてくるデータ(エクセル)を自社のデータシートに変換するツールを作成して欲しい。 今後2万件程増える予定。 | G60: データを変換するプログラムを作成して自動化します。 | H60: - | I60: 完了 | K60: 7/10に完了済み。 | N60: 25
B61: =ROW()-3 -> 58 | C61: 45847 | D61: 商品部 | E61: 売れ筋商品の取得 | F61: アスクルの各カテゴリの売れ筋の商品情報を抜き出したい。 | G61: アスクルのカテゴリ別ランキングページから商品情報を取得します。 | H61: 急ぎ | I61: 完了 | K61: 7/10に完了済み。 | N61: 25
B62: =ROW()-3 -> 59 | C62: 45848 | D62: 営業管理部 商品管理課 | E62: ファースト未登録品の調査 | F62: 登録件数目標達成のため、ファーストの分類誤りで登録できなかった分 を登録できるようにする→スピードアップしたい。 | G62: フォーレストの分類がアズワンのカテゴリを模しているとのことで 商品をアズワンで検索した結果の分類を取得する自動プログラムを作成して作業時間短縮を図る。 | H62: - | I62: 完了 | K62: 1件あたり約2.8分→約0.4分に短縮。 約83.3％の時間効率改善。 | N62: 25
B63: =ROW()-3 -> 60 | C63: 45861 | D63: 管理部 債権・請求管理課 | E63: 納品書・請求書のPDF化 | F63: お客様に請求書・納品書をPDFで送付したいが、現状のSCAWの出力メニューではプリンタに直接出力されてしまう。そのため、紙で印刷したものをスキャンしてPDF化しており、紙資源と作業時間が無駄になっている。 | G63: 福岡システムと連携し、出力をプリンタではなく画面表示に変更してもらうことで、基幹システム側でPDF出力可能なプリンタドライバを使用してPDF化できるようにする。 | H63: - | I63: 完了 | K63: 7/24に完了済み。 | N63: 25
B64: =ROW()-3 -> 61 | C64: 45868 | D64: 商品部 | E64: エディオン商品の画像取得 | F64: エディオン仕入れで販売する画像をエディオンサイトから取得したい。 | G64: プログラムを作成して自動取得します。 | H64: - | I64: 完了 | K64: 7/30に完了済み。 ツール化済み。 | N64: 25
B65: =ROW()-3 -> 62 | C65: 45876 | D65: 商品部 | E65: DCMの在庫アイテム取得 | F65: DCMで在庫を持ってるアイテム情報が欲しい。 | G65: プログラムを作成して自動取得します。 | H65: - | I65: 完了 | K65: 7/18に完了済み。 | N65: 25
B66: =ROW()-3 -> 63 | C66: 45890 | D66: 営業管理部 商品管理課 | E66: 基幹データ抽出ツール | F66: ・基幹のデータを取得するのに品目コードで指定したいが品目コードが８万件ぐらいあるので、一度対象のUP_DT(更新日付)を更新して、その日付を指定してデータを取得する運用にしていた。 →他の業務でデータの更新があるため、業務の一番最後にやるしか方法がなかった。 これを改善したい。 | G66: インプットされたエクセルから品目コードを抽出して、SQLの条件にしてデータを取得できるプログラムを作成します。 | H66: - | I66: 完了 | K66: 8/22に完了済み。 作業時間： ４～６時間×２人 → 2～3分× 1人 所要時間の削減率は約 99.4% | N66: 25
B67: =ROW()-3 -> 64 | C67: 45900 | D67: 商品部 商品課 | E67: マスター抽出ツールの改善 | F67: マスター抽出するツール（インプロ）の結果が出るのが時間がかかる。 （４０～６０分ぐらい） | G67: インプロの中身（SQL）を調査して最適化します。 | H67: - | I67: 完了 | K67: 9/8に完了済み。 約５０分 → 約２分 所要時間の削減率は約 96% | N67: 25
B68: =ROW()-3 -> 65 | C68: 45909 | D68: 商品部 商品課 | E68: まとめ売りの画像作成 | F68: 冷凍食品の画像でまとめ売りの画像にピクトを入れたい。 | G68: プログラムを作成して自動化します。 | H68: なるべく早め | I68: 完了 | K68: 9/9に完了済み。 手動で9～10時間かかるのが、１～２分で完了。 所要時間の削減率は約 99.7%。 ツール化して汎用的に使えるようにしました。 | N68: 25
B69: =ROW()-3 -> 66 | C69: 45912 | D69: 商品部 商品課 | E69: アスクルデータ取得 | F69: アスクルが在庫を持ってる商品を調査したい。 | G69: スクレイピングで直送以外のデータを調査します。 | H69: 最優先 | I69: 完了 | J69: レンタルサーバー6台借りて調査中。 アイテム数が1500万点以上あるので調査にかなり時間を要します。 9/16 10時の時点で132万点完了済み。 カテゴリ毎に抽出して終わり次第提出します。 | K69: 9/19(金)： 18カテゴリ中９カテゴリ取得済みで自社マスタをマージして提出済み。 残りも引き続き取得中。 9/20(土)： 「カウネット」「たのめーる」の在庫状況も取得したいとのことで 別途プログラム作成し、「カウネット」「たのめーる」の情報を取得。 ５カテゴリ取得完了し、結果をマージして提出済み。 残りも引き続き取得中。 9/22(月)： ・アスクル 600/1,500万点取得済み 17/18カテゴリ 残り「機械部品／空圧機器／電気・電子部品」約900万点 →安形部長よりこのカテゴリは不要との事でアスクルは終了。 ・カウネット＆たのめーるデータ 10/18カテゴリ取得済み 9/24(火)： ・依頼のデータ全て完了して提出済み。 ・総検索数 アスクル：約６００万点 カウネット、たのめーる：約４１万点 | N69: 25
B70: =ROW()-3 -> 67 | C70: 45919 | D70: 営業部 | E70: 基幹データ抽出ツール | F70: ・フォレストウェイ全体の商品マスタデータを基幹から取得するのに８０万件ぐらいあるので、一度抜くのに2～4時間くらいかかる これを改善したい。 作業時間：ＰＣ占有時間2～3時間 | G70: インプロの中身（SQL）を調査して最適化します。 | H70: なるべく早め | I70: 完了 | K70: 9/20(土)： ・着手中 9/22(月)： ・SQLを作成して基幹メールで提出済み。 ・結果のフィードバック待ち。 | L70: 一カ月で今までかかっていた作業が ５２０分から１８０分に短縮できたとのこと。 → 作業時間の約６５．４％削減 | N70: 25
B71: =ROW()-3 -> 68 | C71: 45926 | D71: 商品部 商品課 | E71: フォーレスト在庫有 かつ アスクル・カウネット・たのめーる の在庫無し情報をとりたい | F71: No.66の延長で フォーレスト在庫有 かつ アスクル・カウネット・たのめーるの在庫有無情報 をとりたい。 | G71: アスクルのデータはあるので、No.66で取得したデータ以外のものを カウネット・たのめーるで情報取得します。 | H71: なるべく早め | I71: 完了 | J71: 取得データアイテム数はカウネット・たのめーる、それぞれで７５万点ほど | K71: 9/26(金)： ・着手中 → データ取得中 9/27(土)： ・データ取得中 データ取得率：カウネット：15％ たのめーる：20％ ・速度を上げるためにプログラム調整を実施 9/29(月) ・データ取得中 データ取得率：カウネット：40％ たのめーる：85％ ・カウネットが遅いのでレンタルサーバー増やして対応 9/30(火)： ・データ取得中 データ取得率：カウネット：70％ たのめーる：100% 10/1(水)： ・データ取得中 データ取得率：カウネット：95％ たのめーる：100% 明日の午前中には終わって提出予定。 10/2(木)： ・フォーレストデータとマージして提出済み。 | N71: 25
B72: =ROW()-3 -> 69 | C72: 45936 | D72: 商品部 商品管理課 | E72: 商品登録に時間がかかってる件 (商品キーワード) | F72: 商品登録でネックになっている内容を自動化 ①キーワード ②キャッチコピー ③機種依存文字・使用不可文字の利用チェック ④社外サイトの分類の選定 | G72: ①キーワード → AIによる自動化 ②キャッチコピー → AIによる自動化 ③機種依存文字・使用不可文字の利用チェック →VBAによるチェック機能 ④社外サイト分類の選定 → AIによる自動化 | H72: なるべく早め | I72: 完了 | J72: 追加要望が多いのでNo.69についてはいったん完了とし、 No.80で再登録します。 | K72: 10/14(火)： 着手中→AIのAPIを利用するための稟議作成→申請中→可決 10/16(木)： ミーティングで登録をスムーズに行うために必要項目（①～④）を選出 ③の機種依存文字の検出完了済み→要修正 10/17(金)： ③の「機種依存文字・使用不可文字の利用チェック」完了済み 10/20(月)： ①キーワード作成→完成 ④社外サイト分類の選定 → 完成 ②は既存のプログラムがあるので終了 10/24(金)： 商品登録PJにて追加要望 | N72: 25
B73: =ROW()-3 -> 70 | C73: 45936 | D73: 商品部 商品管理課 | E73: 商品登録に時間がかかってる件 (商品登録画像) | F73: 仕入先から送られてきた画像がフォーレストの画像の大きさとあってないので 画像を加工しないといけない | G73: プログラムを作成して一括編集できるようにします | H73: なるべく早め | I73: 完了 | J73: リサイズはオッケー。 仕入先から来る画像データの並び順でそのまま画像登録すると背面画像が途中にきてしまうので、仕入先から来る画像のリネームをする必要あり。 →リサイズとリネーム二つのプログラムで対応。 | K73: 10/8(水)： ・着手 → 完成 → 検証依頼中 →追加要望「商品の背面画像は並び順で一番後ろにしたい」 10/9(木)： ・追加要望着手中 → GUIで指定した画像をトップ画像、背面画像にリネームできるツールを別途作成 10/10(金)： ・一部画像が縦1200を超えてしまうバグ修正 ・背面画像は３つまで必要とのことで対応済み(追加要望) →追加要望あり 対応検討中 10/17(金)： ・着手中 → 追加要望対応版提供済み | N73: 25
B74: =ROW()-3 -> 71 | C74: 45937 | D74: 商品部 商品課 | E74: チルド売価設定の為のデータ抽出 | F74: 冷凍食品の売価を設定するのに、商品の売価と送料を取得したい | G74: プログラムでスクレイピングします | H74: なるべく早め | I74: 完了 | K74: 10/8(水)： ・着手→完成→データ提出済み | L74: ・人がやったらと仮定したら １アイテム3分45秒として×2,000アイテム＝125時間/人 プログラムで取得した時間＝10時間 → 作業時間の約９２％削減 | N74: 25
B75: =ROW()-3 -> 72 | C75: 45940 | D75: 商品部 商品課 | E75: キャッチコピー作成 | F75: 冷凍食品のデータをアップしたがキャッチコピーが未設定なので 作成したい。(約１６００件) | G75: OpenAIのAPIを使って、商品名・商品説明からキャッチコピーを作成します。 | I75: 完了 | J75: 結果の精度があまり良くないので、 今後のためにチューニング方法を検討中。 | K75: 10/10(金)： ・着手→完成 | L75: ・実績：１６００件で約２０分 人がやった場合の想定時間：１件３０秒としても１３時間２０分 → 作業時間の約９７．４％削減 | N75: 25
B76: =ROW()-3 -> 73 | C76: 45944 | D76: 営業管理部 事業管理課 | E76: SCAWとデータウェアハウス連携 | F76: 基幹SCAWデータ取得→OAGoogleCloudoStrage保存→BigQueryテーブル更新を自動化したい | G76: pythonプログラムで自動化します。 | H76: １1月中 （早ければ10月中） | I76: 完了 | K76: 10/14(火)： ・着手 10/15(水)： ・基幹でデータ取得してOA側に移動の自動化完了 10/25(土)： ・土日祝分のデータを営業日にまとめるコード追加 11/20(木)： ・CSVのGoogleCloudアップロードまで自動化 11/27(木)： ・顧客データ、商品データのbigquery登録まで自動化 11/28(土)： ・受注残データのbigqueryOK。 12/01(月)： ・受注データの更新(追記)テスト→OK 12/03(水)： ・受注データ、売上データの更新の自動化完了 12/05(金)： ・全データ連携完了 | L76: 毎日４５分の削減 | N76: 25
B77: =ROW()-3 -> 74 | C77: 45945 | D77: 営業部 | E77: 弊社長期欠品商品の他社クローリング | F77: 長期欠品リストを基にアスクルの販売状況の確認 | G77: No66で対応したプログラムがあるのでツール化します。 | H77: １1月中 （早ければ10月中） | I77: 完了 | K77: 11/14(金)： ・着手 11/19(水)： ・完成→検証中 11/20(木)： ・検索スピードアップ対応→検証中 11/21(金)： ・完了 | L77: 10時間/月の削減 | N77: 25
B78: =ROW()-3 -> 75 | C78: 45946 | D78: 営業部 | E78: 個別単価設定商品の確認 | F78: 営業用に商品に単価設定を実施するが、 チェックがエクセルベースになっており煩雑。 原価値上げの際、チェックされないため赤字販売の可能性がある。 | G78: 未対応 | H78: １1月中 （早ければ10月中） | I78: 完了 | J78: 長谷川さんが対応しました | N78: 25
B79: =ROW()-3 -> 76 | C79: 45947 | D79: 商品部 PB事業課 | E79: 競合他社のPB品抽出 | F79: 「アスクル」「カウネット」「たのめーる」のPB品の情報を取得したい。 | G79: スクレイピングで情報を取得します。 | H79: - | I79: 完了 | J79: カウネット、たのめーるは未対応。 WEBデータにJANがないため、弊社情報と紐づけられない。 それでも必要か確認中。 →カテゴリやジャンルが必要なのでJANは不要 | K79: 10/25(土)： ・着手→アスクル分の取得完了 データは社内メールで送信済み 11/14(金)： ・今回は手作業で確認したので、今後チェックするのにツール化希望とのこと。 01/10(土)： No９４～９６で完了済み | N79: 25
B80: =ROW()-3 -> 77 | C80: 45952 | D80: 顧客部 サービス課 | E80: 名刺 既存顧客の新規購入の確認 | F80: 中分類3005の既存顧客の新規作成を確認し、リピートにつなげるべく、困っていることが無いかメール送信予定 | G80: SQLを作成します。 | H80: 今週中 | I80: 完了 | K80: 10/22(水)： 着手 → 完了 | N80: 25
B81: =ROW()-3 -> 78 | C81: 45952 | D81: 商品部 在庫管理課 | E81: データ取得関連業務の自動化 | F81: 基幹SCAW及びツールによるデータ取得→指定形式、指定場所への保存 | G81: pythonプログラムで自動化します。 | H81: １1月中 （早ければ10月中） | I81: 終了 | J81: imr→SQLに時間がかかるのと、商品登録優先のため１１月中は難しいです。 | K81: 05/07(木)： 対応に時間がかかる為、津田課長と相談し終了とさせていただきました。 | N81: -
B82: =ROW()-3 -> 79 | C82: 45961 | D82: 西日本営業所 | E82: 見積書に必要なデータの取得 | F82: 見積作成に必要な項目について、検索キーをもとに簡単に抽出で切るような仕組みを作ってほしい。 現状１商品に１０～２０分以上かかっている。 （案件によるが２０～１５０アイテム） | G82: プログラムを作って可能な限り実現します。 | H82: できるだけ早く | I82: 完了 | J82: 検索先は 「アスクル、たのめーる、モノタロウ、楽天、ヨドバシ」 データ取得は工数がかかるので、取り急ぎ検索リンクをつけて対応 | K82: 10/31(金)： ・着手→完了 確認は週明けになるそう。 細かい修正があればその都度対応します。 11/05(水)： 追加依頼あり→完了→確認OK | L82: ２５アイテムだとこれまで4時間弱のところ20分 削減効率 = 220分 ÷ 240分 × 100% = 0.9166... × 100% = 91.67% 件数が増えれば増えるほど、これまでとくらべて効率が良くなるとのこと。 | N82: 25
B83: =ROW()-3 -> 80 | C83: 45961 | D83: 商品部 商品管理課 | E83: 商品登録に時間がかかってる件 ・機種依存文字・使用不可文字の利用チェック | F83: 商品登録でネックになっている内容を自動化してほしい ・機種依存文字・使用不可文字の利用チェック | G83: ツール（VBA）を作成して実現します。 | H83: 最優先 | I83: 完了 | K83: 10/31(金)： ・着手→完了→確認待ち→確認OK | N83: 25
B84: =ROW()-3 -> 81 | C84: 45961 | D84: 商品部 商品管理課 | E84: 商品登録に時間がかかってる件 ・既存マスタとの重複チェック | F84: 商品登録でネックになっている内容を自動化してほしい ・既存マスタとの重複チェック | G84: ツール（VBA）を作成して実現します。 →Pythonによるプログラムに変更 | H84: 最優先 | I84: 完了 | K84: 10/31(金)： ・着手→完了→確認待ち→確認NG 11/05(水)： ・修正中→確認待ち→完了 11/10(月))： ・仕様変更依頼→完了→確認待ち | N84: 25
B85: =ROW()-3 -> 82 | C85: 45961 | D85: 商品部 商品管理課 | E85: 商品登録に時間がかかってる件 ・品目名カナ修正 | F85: 商品登録でネックになっている内容を自動化してほしい ・品目名カナ修正 漢字などの全角文字を自動で半角カナにして欲しい | G85: 数式で読み仮名を表示できるが、入力側が手作業で入力していないと読み仮名が反映されないので、AIを利用して読み仮名を入力します。 | H85: 最優先 | I85: 完了 | K85: 10/31(金)： ・着手→仕様を確認中 11/05(水)： ・完了→確認待ち→確認OK 11/10(月))： ・仕様変更依頼→完了→確認待ち | N85: 25
B86: =ROW()-3 -> 83 | C86: 45961 | D86: 商品部 商品管理課 | E86: 商品登録に時間がかかってる件 ・分類の選定 | F86: 商品登録でネックになっている内容を自動化してほしい ・分類の選定 | G86: データシートの分類に抜けがある箇所に対してAIを利用して 分類コードを補填するプログラムを作成中 | H86: 最優先 | I86: 完了 | J86: アスクル対策で医療・介護用品のデータシート作成支援にも使えるので それまでに作成したい。 | K86: 11/18(水)： ・着手中 11/29(土)： ・完了→検証→問題なし | L86: １アイテム ２分→５秒 約９５％の時間短縮 | N86: 25
B87: =ROW()-3 -> 84 | C87: 45961 | D87: 商品部 商品管理課 | E87: 商品登録に時間がかかってる件 ・キャッチコピー | F87: 商品登録でネックになっている内容を自動化してほしい ・キャッチコピー | G87: データシートに対してキャッチコピーが抜けてる項目に対して AIを利用したキャッチコピーを入力します。 | H87: 最優先 | I87: 完了 | K87: 10/31(金)： ・着手→完了→確認待ち→確認OK | N87: 25
B88: =ROW()-3 -> 85 | C88: 45961 | D88: 商品部 商品管理課 | E88: 商品登録に時間がかかってる件 ・画像のリサイズ | F88: 仕入先からくる画像をForest仕様のサイズでリサイズしたい | G88: プログラムで対応します | H88: 最優先 | I88: 完了 | K88: No70で対応済み | N88: 25
B89: =ROW()-3 -> 86 | C89: 45961 | D89: 商品部 商品管理課 | E89: 商品登録に時間がかかってる件 ・画像のリネーム | F89: 下記を自動化したい ・画像のナンバリング（JANの前にDSの行NO.をつける）例）1●4972814531680.jpg ・DS順に全画像を確認 ・同枚数ごとに確認 ・11枚以上の選別（選んだ画像を不要へ移動） ・4枚以上ある裏面の選別（選んだ裏面を「裏面フォルダ」へ移動。ナンバリング状態のまま） ・メインのみの表示 ・メインに背景があったら商品の切り抜き ・画像の入れ替え（メインとサブの入替） ・画像の複製（指定したJANを複製し画像名の変更）青だけにサブがあり、他の色にはメインしかない ・リネームする ・リネーム後のメイン画像の頭に★を付ける（ピクトを入れる） | G89: プログラムを作成します。 | H89: 最優先 | I89: 完了 | K89: 11/22(土)： ・着手 01/14(水)： ・完了 | N89: 25
B90: =ROW()-3 -> 87 | C90: 45974 | D90: 商品部 商品課 | E90: アスクル・ソロエルアリーナでの 販売再開商品の情報取得 | F90: 医療・介護向け商品の取り扱いを強化するため、 アスクルソロエルアリーナで販売再開する商品情報を取得したい。 | G90: スクレイピングで情報取得します | H90: なるべく早め | I90: 完了 | K90: 11/13(木)： 着手→完了 | L90: 人がやったらと仮定したら １アイテム20秒として×約757商品＝約250時間/人 | N90: 25
B91: =ROW()-3 -> 88 | C91: 45974 | D91: マーケティング部 サイト運営課 | E91: 商品名に対してキーワードを追加する作業の自動化 | F91: エクセルのVLOOKUPとマクロを使って商品名に対してキーワードを追加し、 そのキーワードを一つずつ組み合わせた商品名を作成ているが時間がかかるので自動化したい。 | G91: プログラムを作成して自動化します | H91: なるべく早め | I91: 完了 | K91: 11/14(金)： 着手→検証待ち→修正中 11/17(月)： 修正済み→検証待ち→完了 | L91: ３０分→５分に短縮で約８３％の削減。 またプログラムによる作業なのでミスがなくなった、とのこと。 | N91: 25
B92: =ROW()-3 -> 89 | C92: 45999 | D92: 商品部 在庫管理課 | E92: 在庫管理課で利用してる既存ツールの改修・改善 | F92: Impromptu販売実績ツールの改修 | G92: インプロを改修して日別と販路別のデータを見える化します | H92: 1月～2月中 | I92: 完了 | K92: 12/08(月)： ①着手→完成→検証待ち | L92: 不明 | N92: 25
A93: . | B93: =ROW()-3 -> 90 | C93: 45999 | D93: 商品部 在庫管理課 | E93: 在庫管理課で利用してる既存ツールの改修・改善 | F93: 長期欠品メンテナンスのデータ作成、マスタ更新 | G93: ①インプロからSQLにする作業(４９項目) ②基盤のシステム(SQLを実行して任意の場所に出力するシステム) の開発が必要。 | H93: 1月～2月中 | I93: 終了 | K93: 01/15(木)： ②着手、進捗５０％ ①着手、1/49完成。 05/07(木)： 対応に時間がかかる為、津田課長と相談し終了とさせていただきました。 | N93: -
B94: =ROW()-3 -> 91 | C94: 45999 | D94: 商品部 在庫管理課 | E94: 在庫管理課で利用してる既存ツールの改修・改善 | F94: 売上抽出ツールの作成 | G94: SQLを修正します | H94: 1月～2月中 | I94: 完了 | K94: 12/10(水)： ③着手→完成→検証待ち | L94: 不明 | N94: 25
B95: =ROW()-3 -> 92 | C95: 46003 | D95: 商品部 商品課 | E95: 社外自動売価作業の作業軽減 | F95: 社外自動売価作業の作業でエクセルのデータ量が多く時間がかかるので改善したい | G95: プログラムを作成します | H95: 12月中 | I95: 完了 | K95: 12/12(金)： 着手→完了 | L95: １５０分→２０分 ８６％の時間削減 | N95: 25
B96: =ROW()-3 -> 93 | C96: 46029 | D96: 商品部 商品管理課 | E96: 品揃え強化 DSが来たか照合するプログラム作成 | F96: 1）WEB-EDIからダウンロードした複数のDSを1つにまとめる（作業者のデスクトップ） 2）別途DS依頼済のリストと、JANコードで照合する（NAS端末上） 3）合致した場合、受け取り日の欄に当日の日付を入れてリストを上書き保存（NAS端末上） | G96: プログラムを作成します | H96: なるべく早め | I96: 完了 | K96: 01/07(水)： 着手→完了 | L96: 毎日15分の作業を完全自動化。月間約5時間の削減。 | N96: 25
B97: =ROW()-3 -> 94 | C97: 46031 | D97: 商品部 商品課 | E97: 他社の価格情報取得 アスクルPB | F97: 他社のPB品の商品情報を取得したい | G97: プログラムを作成します | H97: 1月中旬 | I97: 完了 | J97: 月１で抽出して、差分を出力できるようにしておきます。 | K97: 01/10(土)： 着手→完了 | N97: 25
B98: =ROW()-3 -> 95 | C98: 46031 | D98: 商品部 商品課 | E98: 他社の価格情報取得 カウネットPB | F98: 他社のPB品の商品情報を取得したい | G98: プログラムを作成します | H98: 1月中旬 | I98: 完了 | J98: 月１で抽出して、差分を出力できるようにしておきます。 | K98: 01/10(土)： 着手→完了 | N98: 25
B99: =ROW()-3 -> 96 | C99: 46031 | D99: 商品部 商品課 | E99: 他社の価格情報取得 たのめーるPB | F99: 他社のPB品の商品情報を取得したい | G99: プログラムを作成します | H99: 1月中旬 | I99: 完了 | J99: 月１で抽出して、差分を出力できるようにしておきます。 | K99: 01/10(土)： 着手→完了 | N99: 25
B100: =ROW()-3 -> 97 | C100: 46031 | D100: 商品部 商品課 | E100: 他社の価格情報取得 フォーレストランクA商品 | F100: フォーレストランクA商品の他社価格を調査したい | G100: 既存のツールがありますが、取れるデータ項目を最新にして提供します | H100: 1月中旬 | I100: 完了 | K100: 01/14(水)： アスクル分着手→完了 01/15(木)： カウネット、たのめーる着手→完了 | N100: 25
B101: =ROW()-3 -> 98 | C101: 46035 | D101: 管理部 債権・請求管理課 | E101: 当日受注分を含めたForestwayの 販路単位での受注税込売上を抽出 | F101: 当日受注分を含めたForestwayの 販路単位での受注税込売上を抽出(顧客cd単位での抽出もできれば尚可) | G101: インプロを修正して販路、顧客CDを指定できるようにします | H101: なるべく早め | I101: 完了 | K101: 01/13(火)： 着手→完了 | N101: 25
...

Sheet ヘルプデスク - 作業内容管理・進捗
D1: システム運営課 ヘルプデスク - 作業内容管理・進捗
B2: No1 | C2: 202606 | D2: 支援 | E2: 伊藤 | F2: 46199.381 | G2: 46199.392 | M2: 佐々嶌さん | N2: 低 | O2: 完了 | P2: DocuWorksのインストールフォルダの場所の共有 | Q2: チャットにて共有を実施。
B3: No2 | C3: 202606 | D3: 支援 | E3: 伊藤 | F3: 46199.441 | G3: 46199.451 | H3: 対応日数(営業日) | I3: 実作業時間 | J3: ジャンル | K3: 依頼部署 | L3: 依頼部署(課) | M3: 宮澤直也様 | N3: 低 | O3: 完了 | P3: 注文書の送付および、配送先の「福岡開発室」への変更依頼 | Q3: メールにて送付と変更依頼を実施。
B4: No3 | C4: 202606 | D4: 支援 | E4: 伊藤 | F4: 46199.448 | G4: 46199.458 | H4: =IF(F4="", "", NETWORKDAYS.INTL(F4, G4, 11,祝日シート!A:A)) -> 1 | I4: 0.16666667 | J4: OA端末関連 | K4: 商品部 | M4: 坂田部長 | N4: 低 | O4: 完了 | P4: UPSバッテリー購入の手配 | Q4: 稟議通過を報告し、Amazonでの購入手配をチャットで依頼。
B5: No4 | C5: 202606 | D5: 支援 | E5: 伊藤 | F5: 46199.478 | G5: 46199.489 | H5: =IF(F5="", "", NETWORKDAYS.INTL(F5, G5, 11,祝日シート!A:A)) -> 1 | I5: 0.083333333 | J5: OA端末関連 | K5: システム部 | M5: 篠嵜様 | N5: 低 | O5: 完了 | P5: スマホ機種変更（2回線）の正式発注と納期確認、ガラホの見積もり確認 | Q5: メールにて発注および確認を実施。
B6: No5 | C6: 202606 | D6: 支援 | E6: 伊藤 | F6: 46202.451 | G6: 46202.462 | H6: =IF(F6="", "", NETWORKDAYS.INTL(F6, G6, 11,祝日シート!A:A)) -> 1 | I6: 0.041666667 | J6: OA端末関連 | K6: システム部 | M6: 髙山さん | N6: 低 | O6: 完了 | P6: 足達さんのアカウント連携トラブル対応 | Q6: デバイス削除と再サインインの手順をチャットで指示。
B7: No6 | C7: 202606 | D7: 支援 | E7: 伊藤 | F7: 46202.547 | G7: 46202.558 | H7: =IF(F7="", "", NETWORKDAYS.INTL(F7, G7, 11,祝日シート!A:A)) -> 1 | I7: 0.020833333 | J7: OA端末関連 | K7: マーケティング部 | M7: 野崎さん | N7: 低 | O7: 完了 | P7: Windows 11環境での基幹端末操作（カーソルずれ）の解消 | Q7: 解消のための設定手順をチャットで伝授し、解決に導く。
B8: No7 | C8: 202606 | D8: 支援 | E8: 伊藤 | F8: 46202.554 | G8: 46202.565 | H8: =IF(F8="", "", NETWORKDAYS.INTL(F8, G8, 11,祝日シート!A:A)) -> 1 | I8: 0.010416667 | J8: 総務関連 | K8: 管理部 | M8: 坂田部長 | N8: 低 | O8: 完了 | P8: 北澤さんの携帯番号重複への対応方針の確認 | Q8: 新規購入とするか交換とするかの判断を仰ぐため、チャットで相談。
B9: No8 | C9: 202606 | D9: 支援 | E9: 伊藤 | F9: 46202.603 | G9: 46202.614 | H9: =IF(F9="", "", NETWORKDAYS.INTL(F9, G9, 11,祝日シート!A:A)) -> 1 | I9: 0.013888889 | J9: 基幹端末関連 | K9: 商品部 | M9: 磯辺さん | N9: 低 | O9: 完了 | P9: 福岡へのガラケー発送対応 | Q9: 発送が完了した旨をチャットで報告。
B10: No9 | C10: 202606 | D10: 支援 | E10: 伊藤 | F10: 46202.607 | G10: 46202.617 | H10: =IF(F10="", "", NETWORKDAYS.INTL(F10, G10, 11,祝日シート!A:A)) -> 1 | I10: 0.010416667 | J10: 基幹端末関連 | K10: マーケティング部 | M10: 佐々嶌さん | N10: 低 | O10: 完了 | P10: PythonのExcelツールエラーに関する野崎さんからの問い合わせ対応 | Q10: エラーの内容を佐々嶌さんへチャットで転送し、状況を共有。
B11: No10 | C11: 202606 | D11: 支援 | E11: 伊藤 | F11: 46202.667 | G11: 46202.678 | H11: =IF(F11="", "", NETWORKDAYS.INTL(F11, G11, 11,祝日シート!A:A)) -> 1 | I11: 0.010416667 | J11: 基幹端末関連 | K11: 商品部 | M11: 下村部長 | N11: 低 | O11: 完了 | P11: 自身の有給取得と通院によるシフト変更届の提出 | Q11: チャットにて連絡・提出。
B12: No11 | C12: 202606 | D12: 支援 | E12: 伊藤 | F12: 46203.349 | G12: 46203.359 | H12: =IF(F12="", "", NETWORKDAYS.INTL(F12, G12, 11,祝日シート!A:A)) -> 1 | I12: 0.20833333 | J12: OA端末関連 | K12: マーケティング部 | M12: 出嶋様 | N12: 低 | O12: 完了 | P12: 購入機器の配送先（大宮本社）および領収書宛名等の情報回答 | Q12: メールにて必要な情報を回答。
B13: No12 | C13: 202606 | D13: 支援 | E13: 伊藤 | F13: 46203.366 | G13: 46203.376 | H13: =IF(F13="", "", NETWORKDAYS.INTL(F13, G13, 11,祝日シート!A:A)) -> 1 | I13: 0.27083333 | J13: ネットワーク | K13: システム部 | M13: 中居様 | N13: 低 | O13: 完了 | P13: Office 2019のKMSホストキーに関する問い合わせ | Q13: メールにて技術的な問い合わせを実施。
B14: No13 | C14: 202606 | D14: 支援 | E14: 伊藤 | F14: 46203.606 | G14: 46203.616 | H14: =IF(F14="", "", NETWORKDAYS.INTL(F14, G14, 11,祝日シート!A:A)) -> 1 | I14: 0.125 | J14: 総務関連 | K14: 商品部 | M14: 髙山さん | N14: 低 | O14: 完了 | P14: 足達さんのスマホ設定エラー対応 | Q14: 設定が上手くいかないため、端末を預かってこちらで再設定する旨をチャットで連絡。
B15: No14 | C15: 202607 | D15: 支援 | E15: 伊藤 | F15: 46204.409 | G15: 46204.419 | H15: =IF(F15="", "", NETWORKDAYS.INTL(F15, G15, 11,祝日シート!A:A)) -> 1 | I15: 0.041666667 | J15: OA端末関連 | K15: システム部 | M15: 石鍋さん | N15: 低 | O15: 完了 | P15: 貯蔵品（PC・ディスプレイ）の数量確認と報告 | Q15: チャットにて現在の在庫数量を報告。
... B22: No21 | C22: 202607 | D22: 支援 | E22: 伊藤 | F22: 46216.495 | G22: 46216.506 | H22: =IF(F22="", "", NETWORKDAYS.INTL(F22, G22, 11,祝日シート!A:A)) -> 1 | I22: 0.0625 | J22: SCAW関連 | K22: 営業管理部 | M22: 坂田部長 | N22: 低 | O22: 完了 | P22: 派遣社員用端末のOffice365ライセンス追加依頼 | Q22: 坂田部長へチャットで追加手配を依頼。
B23: ="No"&ROW()-3 -> No20 | C23: =IFERROR(IF(G23<>"",TEXT(G23,"yyyymm"),""),"") -> 202408 | D23: 運用 | E23: 伊藤 | F23: 45522.667 | G23: 45522.688 | H23: =IF(F23="", "", NETWORKDAYS.INTL(F23, G23, 11,祝日シート!A:A)) -> 0 | I23: 0.020833333 | J23: 総務関連 | K23: 商品部 | M23: 小幡 | N23: 低 | O23: 完了 | P23: 小幡用ノートPCのキッティング作業 田中・加藤 商品管理部 Scawメニュー付与 | Q23: 左記の内容で実施。
B24: ="No"&ROW()-3 -> No21 | C24: =IFERROR(IF(G24<>"",TEXT(G24,"yyyymm"),""),"") -> 202408 | D24: 運用 | E24: 伊藤 | F24: 45529.375 | G24: 45529.708 | H24: =IF(F24="", "", NETWORKDAYS.INTL(F24, G24, 11,祝日シート!A:A)) -> 0 | I24: 0.33333333 | J24: 総務関連 | K24: マーケティング部 | M24: 山本 | N24: 低 | O24: 完了 | P24: 山本ノートPCキッティング（作業用スクリプト制作含む） | Q24: 左記の内容で実施。
B25: ="No"&ROW()-3 -> No22 | C25: =IFERROR(IF(G25<>"",TEXT(G25,"yyyymm"),""),"") -> 202408 | D25: 障害 | E25: 伊藤 | F25: 45529.458 | G25: 45529.465 | H25: =IF(F25="", "", NETWORKDAYS.INTL(F25, G25, 11,祝日シート!A:A)) -> 0 | I25: 0.0069444444 | J25: OA端末関連 | K25: 社長 | M25: 尾島社長 | N25: 低 | O25: 完了 | P25: 尾島社長OA端末フリーズ対応 | Q25: タスクマネージャで不要アプリの停止などで動作が復旧。
B26: ="No"&ROW()-3 -> No23 | C26: =IFERROR(IF(G26<>"",TEXT(G26,"yyyymm"),""),"") -> 202408 | D26: 支援 | E26: 伊藤 | F26: 45529.493 | G26: 45529.5 | H26: =IF(F26="", "", NETWORKDAYS.INTL(F26, G26, 11,祝日シート!A:A)) -> 0 | I26: 0.0069444444 | J26: OA端末関連 | K26: 商品部 | M26: 清國 | N26: 低 | O26: 完了 | P26: 清國さん大容量メールの送信をサポート（ギガファイル便の使用） | Q26: 左記の内容で実施。
B27: ="No"&ROW()-3 -> No24 | C27: =IFERROR(IF(G27<>"",TEXT(G27,"yyyymm"),""),"") -> 202408 | D27: 支援 | E27: 伊藤 | F27: 45529.562 | G27: 45529.569 | H27: =IF(F27="", "", NETWORKDAYS.INTL(F27, G27, 11,祝日シート!A:A)) -> 0 | I27: 0.0069444444 | J27: OA端末関連 | K27: 顧客部 | M27: 林田 | N27: 低 | O27: 完了 | P27: 林田さんも同様の質問があり対応 | Q27: 左記の内容で実施。
B28: ="No"&ROW()-3 -> No25 | C28: =IFERROR(IF(G28<>"",TEXT(G28,"yyyymm"),""),"") -> 202408 | D28: 運用 | E28: 伊藤 | F28: 45531.375 | G28: 45531.75 | H28: =IF(F28="", "", NETWORKDAYS.INTL(F28, G28, 11,祝日シート!A:A)) -> 1 | I28: 0.375 | J28: 総務関連 | K28: 顧客部 | M28: 岡本 | N28: 低 | O28: 完了 | P28: 顧客部新入社パート端末キッティング（Docuworks、CTIの設定の資料化、動作確認含む） | Q28: 左記の内容で実施。
B29: ="No"&ROW()-3 -> No26 | C29: =IFERROR(IF(G29<>"",TEXT(G29,"yyyymm"),""),"") -> 202408 | D29: 運用 | E29: 伊藤 | F29: 45531.458 | G29: 45531.479 | H29: =IF(F29="", "", NETWORKDAYS.INTL(F29, G29, 11,祝日シート!A:A)) -> 1 | I29: 0.020833333 | J29: 総務関連 | K29: システム部 | M29: 佐々嶌 | N29: 高 | O29: 完了 | P29: EDI稟議書の作成と修正 | Q29: 左記の内容で実施。
B30: ="No"&ROW()-3 -> No27 | C30: =IFERROR(IF(G30<>"",TEXT(G30,"yyyymm"),""),"") -> 202408 | D30: 支援 | E30: 伊藤 | F30: 45531.5 | G30: 45531.583 | H30: =IF(F30="", "", NETWORKDAYS.INTL(F30, G30, 11,祝日シート!A:A)) -> 1 | I30: 0.083333333 | J30: 業務運用 | K30: 物流部 | N30: 中 | O30: 完了 | P30: 東日本物流 複合機入替作業 設定の残作業を実施 | Q30: 左記の内容で実施。
B31: ="No"&ROW()-3 -> No28 | C31: =IFERROR(IF(G31<>"",TEXT(G31,"yyyymm"),""),"") -> 202408 | D31: 支援 | E31: 伊藤 | F31: 45532.375 | G31: 45532.75 | H31: =IF(F31="", "", NETWORKDAYS.INTL(F31, G31, 11,祝日シート!A:A)) -> 1 | I31: 0.375 | J31: 総務関連 | K31: 顧客部 | M31: 岡本 | N31: 低 | O31: 完了 | P31: 顧客部新入社パート端末キッティング（Docuworks、CTIの設定の資料化、動作確認含む） | Q31: 左記の内容で実施。
B32: ="No"&ROW()-3 -> No29 | C32: =IFERROR(IF(G32<>"",TEXT(G32,"yyyymm"),""),"") -> 202408 | D32: 支援 | E32: 伊藤 | F32: 45532.542 | G32: 45532.667 | H32: =IF(F32="", "", NETWORKDAYS.INTL(F32, G32, 11,祝日シート!A:A)) -> 1 | I32: 0.125 | J32: 業務運用 | K32: 物流部 | N32: 中 | O32: 完了 | P32: 東日本物流 複合機入替作業 設定の残作業を実施 | Q32: ドライバの確認、基幹側は旧ドライバから設定変更し流用？
B33: ="No"&ROW()-3 -> No30 | C33: =IFERROR(IF(G33<>"",TEXT(G33,"yyyymm"),""),"") -> 202408 | D33: 障害 | E33: 伊藤 | F33: 45532.625 | G33: 45532.646 | H33: =IF(F33="", "", NETWORKDAYS.INTL(F33, G33, 11,祝日シート!A:A)) -> 1 | I33: 0.020833333 | J33: OA端末関連 | K33: 商品部 | M33: 清國 | N33: 低 | O33: 完了 | P33: 清國さんEXCELのエラーからのデータ復旧 | Q33: 自動保存から別ディレクトリに保管されたデータから復旧。
B34: ="No"&ROW()-3 -> No31 | C34: =IFERROR(IF(G34<>"",TEXT(G34,"yyyymm"),""),"") -> 202408 | D34: 運用 | E34: 伊藤 | F34: 45533.375 | G34: 45533.75 | H34: =IF(F34="", "", NETWORKDAYS.INTL(F34, G34, 11,祝日シート!A:A)) -> 1 | I34: 0.375 | J34: 総務関連 | K34: 顧客部 | M34: 岡本 | N34: 低 | O34: 完了 | P34: 顧客部新入社パート端末キッティング（Docuworks、CTIの設定の資料化、動作確認含む） | Q34: 左記の内容で実施。
B35: ="No"&ROW()-3 -> No32 | C35: =IFERROR(IF(G35<>"",TEXT(G35,"yyyymm"),""),"") -> 202408 | D35: 支援 | E35: 伊藤 | F35: 45533.583 | G35: 45533.625 | H35: =IF(F35="", "", NETWORKDAYS.INTL(F35, G35, 11,祝日シート!A:A)) -> 1 | I35: 0.041666667 | J35: OA端末関連 | K35: システム部 | N35: 低 | O35: 完了 | P35: WindowsUpdate用の運用方法を確認 | Q35: 個々PCで設定し、部署単位で運用？ スクリプトかレジストリ？ グループポリシー変更でどうにかならないか？
B36: ="No"&ROW()-3 -> No33 | C36: =IFERROR(IF(G36<>"",TEXT(G36,"yyyymm"),""),"") -> 202408 | D36: 支援 | E36: 伊藤 | F36: 45533.708 | G36: 45533.75 | H36: =IF(F36="", "", NETWORKDAYS.INTL(F36, G36, 11,祝日シート!A:A)) -> 1 | I36: 0.041666667 | J36: 総務関連 | K36: 顧客部 | M36: 林田 | N36: 低 | O36: 完了 | P36: 顧客部端末の設置作業、林田さんとの内容確認 | Q36: 設置場所、アプリのライセンスの有無で設置場所を変更。
B37: ="No"&ROW()-3 -> No34 | C37: =IFERROR(IF(G37<>"",TEXT(G37,"yyyymm"),""),"") -> 202409 | D37: 運用 | E37: 伊藤 | F37: 45536.375 | G37: 45536.75 | H37: =IF(F37="", "", NETWORKDAYS.INTL(F37, G37, 11,祝日シート!A:A)) -> 0 | I37: 0.375 | J37: 総務関連 | K37: 物流部 | M37: 相原 | N37: 低 | O37: 完了 | P37: 相原 移動に伴う端末のキッティング | Q37: 左記の内容で実施。
B38: ="No"&ROW()-3 -> No35 | C38: =IFERROR(IF(G38<>"",TEXT(G38,"yyyymm"),""),"") -> 202409 | D38: 障害 | E38: 伊藤 | F38: 45536.458 | G38: 45536.469 | H38: =IF(F38="", "", NETWORKDAYS.INTL(F38, G38, 11,祝日シート!A:A)) -> 0 | I38: 0.010416667 | J38: OA端末関連 | K38: 商品部 | M38: 成川 | N38: 低 | O38: 完了 | P38: 成川 Excelが遅く開けない。（北山も同様） | Q38: xlsx形式→xlsb形式でローカルは作業。NWを切断することで動作が若干改善。365特有の問題？
B39: ="No"&ROW()-3 -> No36 | C39: =IFERROR(IF(G39<>"",TEXT(G39,"yyyymm"),""),"") -> 202409 | D39: 運用 | E39: 伊藤 | F39: 45537.375 | G39: 45537.75 | H39: =IF(F39="", "", NETWORKDAYS.INTL(F39, G39, 11,祝日シート!A:A)) -> 1 | I39: 0.375 | J39: 総務関連 | K39: 物流部 | M39: 相原 | N39: 低 | O39: 完了 | P39: 相原 移動に伴う端末のキッティング | Q39: 左記の内容で実施。
B40: ="No"&ROW()-3 -> No37 | C40: =IFERROR(IF(G40<>"",TEXT(G40,"yyyymm"),""),"") -> 202409 | D40: 障害 | E40: 伊藤 | F40: 45537.458 | G40: 45537.465 | H40: =IF(F40="", "", NETWORKDAYS.INTL(F40, G40, 11,祝日シート!A:A)) -> 1 | I40: 0.0069444444 | J40: 基幹端末関連 | K40: 商品部 | M40: 安形 | N40: 低 | O40: 完了 | P40: 安形基幹端末の映像出力できない状況への対応。 | Q40: 基幹PCがフリーズしていたので再起動とチェックディスク実施。切替器の再読み込み。キーボード、マウスも無線で電池交換。
B41: ="No"&ROW()-3 -> No38 | C41: =IFERROR(IF(G41<>"",TEXT(G41,"yyyymm"),""),"") -> 202409 | D41: 障害 | E41: 伊藤 | F41: 45537.458 | G41: 45537.562 | H41: =IF(F41="", "", NETWORKDAYS.INTL(F41, G41, 11,祝日シート!A:A)) -> 1 | I41: 0.10416667 | J41: OA端末関連 | K41: 商品部 | M41: 成川 | N41: 低 | O41: 完了 | P41: Excelの動作が遅くなる問題について確認。xlsx形式→xlsb形式で動作、容量が軽減1/5程度に。 | Q41: xlsx形式→xlsb形式でローカルは作業。NWを切断することで動作が若干改善。365特有の問題？
B42: ="No"&ROW()-3 -> No39 | C42: =IFERROR(IF(G42<>"",TEXT(G42,"yyyymm"),""),"") -> 202409 | D42: 障害 | E42: 伊藤 | F42: 45537.5 | G42: 45537.542 | H42: =IF(F42="", "", NETWORKDAYS.INTL(F42, G42, 11,祝日シート!A:A)) -> 1 | I42: 0.041666667 | J42: SCAW関連 | K42: 営業管理部 | M42: 堀川 | N42: 低 | O42: 完了 | P42: 堀川 基幹 oracleに接続できない問題。oraファイルの内容が古く接続先が違っていたので修正。 | Q42: 左記の内容で実施。
B43: ="No"&ROW()-3 -> No40 | C43: =IFERROR(IF(G43<>"",TEXT(G43,"yyyymm"),""),"") -> 202409 | D43: 要望 | E43: 伊藤 | F43: 45538.375 | G43: 45538.75 | H43: =IF(F43="", "", NETWORKDAYS.INTL(F43, G43, 11,祝日シート!A:A)) -> 1 | I43: 0.375 | J43: その他 | K43: 営業管理部 | M43: 野崎 | N43: 中 | O43: 完了 | P43: 商品管理部 加藤・田中 情報系端末のScawメニューの付与（設定方法の確認も含む） | Q43: 左記の内容で実施。
B44: ="No"&ROW()-3 -> No41 | C44: =IFERROR(IF(G44<>"",TEXT(G44,"yyyymm"),""),"") -> 202409 | D44: 支援 | E44: 伊藤 | F44: 45538.458 | G44: 45538.479 | H44: =IF(F44="", "", NETWORKDAYS.INTL(F44, G44, 11,祝日シート!A:A)) -> 1 | I44: 0.020833333 | J44: 業務運用 | K44: 物流部 | N44: 中 | O44: 完了 | P44: 物流 複合機の設定の確認 | Q44: 基幹のドライバが新しいものはXPで対応していないので旧ドライバから引継ぎ。まだわからない。
B45: ="No"&ROW()-3 -> No42 | C45: =IFERROR(IF(G45<>"",TEXT(G45,"yyyymm"),""),"") -> 202409 | D45: 運用 | E45: 伊藤 | F45: 45538.5 | G45: 45538.583 | H45: =IF(F45="", "", NETWORKDAYS.INTL(F45, G45, 11,祝日シート!A:A)) -> 1 | I45: 0.083333333 | J45: 業務運用 | K45: システム部 | N45: 低 | O45: 完了 | P45: 資産管理 端末情報の確認作業 | Q45: 台帳とSkyの際が増えてきたので現場と在庫と確認。
B46: ="No"&ROW()-3 -> No43 | C46: =IFERROR(IF(G46<>"",TEXT(G46,"yyyymm"),""),"") -> 202409 | D46: 要望 | E46: 伊藤 | F46: 45538.562 | G46: 45538.569 | H46: =IF(F46="", "", NETWORKDAYS.INTL(F46, G46, 11,祝日シート!A:A)) -> 1 | I46: 0.0069444444 | J46: その他 | K46: 営業管理部 | M46: 野崎 | N46: 中 | O46: 完了 | P46: 商品管理部 加藤・田中 固定電話の受信時の動作の変更作業 | Q46: 部署の先に在籍していた社員の設定を流用、設定し確認。手順を資料化して保存。
B47: ="No"&ROW()-3 -> No44 | C47: =IFERROR(IF(G47<>"",TEXT(G47,"yyyymm"),""),"") -> 202505 | D47: 障害 | E47: 伊藤 | F47: 45772.333 | G47: 45778.375 | H47: =IF(F47="", "", NETWORKDAYS.INTL(F47, G47, 11,祝日シート!A:A)) -> 6 | I47: 0.16666667 | J47: OA端末関連 | K47: 物流部 | M47: 山中 | N47: 中 | O47: 完了 | P47: 川口3階のアルバイト・パート社員打刻PCの不調、Freeeの打刻アプリの更新ができない。リモート接続できず本社に送り対応。 | Q47: SSDの不良がありコピーし移植。BIOSなどの更新含め対応。管理部でFreeeの設定を行い発送。設置後にテストをしてもらい、完了。
B48: ="No"&ROW()-3 -> No45 | C48: =IFERROR(IF(G48<>"",TEXT(G48,"yyyymm"),""),"") -> 202505 | D48: 要望 | E48: 坂本 | F48: 45778.365 | G48: 45778.375 | H48: =IF(F48="", "", NETWORKDAYS.INTL(F48, G48, 11,祝日シート!A:A)) -> 1 | I48: 0.010416667 | J48: 業務運用 | K48: 物流部 | M48: 中澤 | N48: 中 | O48: 完了 | P48: 基本ドライバースケジュール変更対応 | Q48: 既定手順で対応済
B49: ="No"&ROW()-3 -> No46 | C49: =IFERROR(IF(G49<>"",TEXT(G49,"yyyymm"),""),"") -> 202505 | D49: 障害 | E49: 伊藤 | F49: 45778.375 | G49: 45778.378 | H49: =IF(F49="", "", NETWORKDAYS.INTL(F49, G49, 11,祝日シート!A:A)) -> 1 | I49: 0.0034722222 | J49: OA端末関連 | K49: 営業部 | M49: 佐藤 | N49: 低 | O49: 完了 | P49: OA端末のログイン時のエラー。画面が黒くなりマウスカーソル以外見えなくなる。 | Q49: Ctrl＋Alt＋Deleteキーでサインアウトし再度ログインすると正常動作でログインできるようになるので解消。Windows11 24H2の障害か？ FMVで多発する。
B50: ="No"&ROW()-3 -> No47 | C50: =IFERROR(IF(G50<>"",TEXT(G50,"yyyymm"),""),"") -> 202505 | D50: 要望 | E50: 伊藤 | F50: 45778.375 | G50: 45778.382 | H50: =IF(F50="", "", NETWORKDAYS.INTL(F50, G50, 11,祝日シート!A:A)) -> 1 | I50: 0.0069444444 | J50: 総務関連 | K50: 管理部 | M50: 関口 | N50: 低 | O50: 完了 | P50: 新入社員 沖田さんのメールアカウントの作成と、サイボウズ への登録・確認。 | Q50: 左記の内容
B51: ="No"&ROW()-3 -> No48 | C51: =IFERROR(IF(G51<>"",TEXT(G51,"yyyymm"),""),"") -> 202505 | D51: 課題 | E51: 伊藤 | F51: 45778.417 | G51: 45778.438 | H51: =IF(F51="", "", NETWORKDAYS.INTL(F51, G51, 11,祝日シート!A:A)) -> 1 | I51: 0.020833333 | J51: その他 | K51: システム部 | M51: 下村 | N51: 低 | O51: 完了 | P51: KPIや業績評価で必要な運営課の作業内容を入力するシートの作成（本シート） | Q51: 作成完了。下村さんにパスを共有するメール。
B52: ="No"&ROW()-3 -> No49 | C52: =IFERROR(IF(G52<>"",TEXT(G52,"yyyymm"),""),"") -> 202505 | D52: 要望 | E52: 坂本 | F52: 45778.417 | G52: 45792.625 | H52: =IF(F52="", "", NETWORKDAYS.INTL(F52, G52, 11,祝日シート!A:A)) -> 13 | I52: 0.041666667 | J52: OA端末関連 | K52: 顧客部 | M52: 遠藤 | N52: 低 | O52: 完了 | P52: オーダーメイドで使用する外付けHDDが認識不可 | Q52: ①外付けHDDを接続する端末を、USBストレージの制限対象外とする ②外付けHDD自体を使用許可するメディアとしてSKYSEA登録して①を解除する
B53: ="No"&ROW()-3 -> No50 | C53: =IFERROR(IF(G53<>"",TEXT(G53,"yyyymm"),""),"") -> 202505 | D53: 障害 | E53: 坂本 | F53: 45778.438 | G53: 45778.521 | H53: =IF(F53="", "", NETWORKDAYS.INTL(F53, G53, 11,祝日シート!A:A)) -> 1 | J53: その他 | K53: 顧客部 | M53: 村本 | N53: 中 | O53: 完了 | P53: 名刺端末でスキャンしたデータが名刺サーバ上(\\flbc01\MEISHI_LOGO\OUT)に存在せず、また見覚えのないデータが存在する | Q53: 社内メールで福岡へ調査依頼 →名刺ロゴ抽出のプログラムが、動作中の状態に見えて一部機能に不具合が発生。プログラムを再起動して解消。
B54: ="No"&ROW()-3 -> No51 | C54: =IFERROR(IF(G54<>"",TEXT(G54,"yyyymm"),""),"") -> 202505 | D54: 障害 | E54: 伊藤 | F54: 45778.479 | G54: 45778.705 | H54: =IF(F54="", "", NETWORKDAYS.INTL(F54, G54, 11,祝日シート!A:A)) -> 1 | I54: 0.03125 | J54: OA端末関連 | K54: 川口配送センター | M54: 中澤 | N54: 中 | O54: 完了 | P54: 中澤さんOA端末 Win11に更新によるものでスキャンボックスに入る際に、 認証が必要となり使用できない。 | Q54: 本社から配送センターの複合機に管理者ログイン。ボックス内の中澤アカウントにパスワードを設定しテスト。11からWindows資格情報にIP、ボックス番号、パスワード設定が必須。総務人事からのフォルダに資料を保管。
B55: ="No"&ROW()-3 -> No52 | C55: =IFERROR(IF(G55<>"",TEXT(G55,"yyyymm"),""),"") -> 202505 | D55: 要望 | E55: 坂本 | F55: 45778.552 | G55: 45778.556 | H55: =IF(F55="", "", NETWORKDAYS.INTL(F55, G55, 11,祝日シート!A:A)) -> 1 | I55: 0.0034722222 | J55: 業務運用 | K55: 営業部 | M55: 佐藤 | N55: 中 | O55: 完了 | P55: 出荷予定日変更 | Q55: 既定手順で対応済
B56: ="No"&ROW()-3 -> No53 | C56: =IFERROR(IF(G56<>"",TEXT(G56,"yyyymm"),""),"") -> 202505 | D56: 支援 | E56: 伊藤 | F56: 45778.708 | G56: 45778.722 | H56: =IF(F56="", "", NETWORKDAYS.INTL(F56, G56, 11,祝日シート!A:A)) -> 1 | I56: 0.013888889 | J56: 総務関連 | K56: 管理部 | M56: 坂田 | N56: 中 | O56: 完了 | P56: Bizストレージ＆ファイルシェア 見積書＆申込書の申し込み・疑問点の確認のためNTTコールセンター担当者と電話。 | Q56: 見積書・申込書はExelファイルでZipファイルでメールで受信予定。週明け。 担当：清水様 0120-950-138
B57: ="No"&ROW()-3 -> No54 | C57: =IFERROR(IF(G57<>"",TEXT(G57,"yyyymm"),""),"") -> 202505 | D57: 支援 | E57: 伊藤 | F57: 45778.722 | G57: 45778.729 | H57: =IF(F57="", "", NETWORKDAYS.INTL(F57, G57, 11,祝日シート!A:A)) -> 1 | I57: 0.0069444444 | J57: その他 | K57: 営業管理部 | M57: 津田 | N57: 低 | O57: 完了 | P57: iPad 業務用アプリケーション更新作業の手順の確認 | Q57: Apple IDを入力し対応。2要素認証が管理部部長だった岡村さんに行くのでGWに修正し変更する予定。
B58: ="No"&ROW()-3 -> No55 | C58: =IFERROR(IF(G58<>"",TEXT(G58,"yyyymm"),""),"") -> 202505 | D58: 問合せ | E58: 佐々嶌 | F58: 45778.729 | G58: 45778.736 | H58: =IF(F58="", "", NETWORKDAYS.INTL(F58, G58, 11,祝日シート!A:A)) -> 1 | I58: 0.0069444444 | J58: その他 | K58: 営業部 | M58: 見形 | N58: 中 | O58: 完了 | P58: メモ番号:36065967の内容が自動的？に入っているが、メールが届いていない。メモ内容がメールと自動連携されているのでメールがあるはず、とのこと。 | Q58: よくわからないので下村さんにお願いしました。
B59: ="No"&ROW()-3 -> No56 | C59: =IFERROR(IF(G59<>"",TEXT(G59,"yyyymm"),""),"") -> 202505 | D59: 要望 | E59: 坂本 | F59: 45779.542 | G59: 45779.552 | H59: =IF(F59="", "", NETWORKDAYS.INTL(F59, G59, 11,祝日シート!A:A)) -> 1 | I59: 0.010416667 | J59: OA端末関連 | K59: 物流部 | M59: 名塚 | N59: 中 | O59: 完了 | P59: OA端末192.176.5.11でUSBメモリの接続許可依頼 | Q59: SKYSEAで接続許可対応
B60: ="No"&ROW()-3 -> No57 | C60: =IFERROR(IF(G60<>"",TEXT(G60,"yyyymm"),""),"") -> 202505 | D60: 問合せ | E60: 坂本 | F60: 45779.594 | G60: 45779.604 | H60: =IF(F60="", "", NETWORKDAYS.INTL(F60, G60, 11,祝日シート!A:A)) -> 1 | I60: 0.010416667 | J60: 基幹端末関連 | K60: 物流部 | M60: 浅野 | N60: 中 | O60: 完了 | P60: 基幹データ移動の際、中継サーバに接続不可。 | Q60: 128.128.5.6のみ疎通ができない状態。再起動後に状況を確認しようとしたが、浅野さんに端末制御が移ったため、メールで接続確認を依頼。
B61: ="No"&ROW()-3 -> No58 | C61: =IFERROR(IF(G61<>"",TEXT(G61,"yyyymm"),""),"") -> 202505 | D61: 支援 | E61: 佐々嶌 坂本 | F61: 45779.792 | G61: 45786.75 | H61: =IF(F61="", "", NETWORKDAYS.INTL(F61, G61, 11,祝日シート!A:A)) -> 7 | I61: 0.33333333 | J61: 開発 | K61: 顧客部 | M61: 野尻 | N61: 中 | O61: 完了 | P61: ライフル買い物コネクトで欠品商品を抽出するツールの仕様変更 | Q61: 要望通り対応
B62: ="No"&ROW()-3 -> No59 | C62: =IFERROR(IF(G62<>"",TEXT(G62,"yyyymm"),""),"") -> 202505 | D62: 障害 | E62: 伊藤 | F62: 45784.375 | G62: 45784.382 | H62: =IF(F62="", "", NETWORKDAYS.INTL(F62, G62, 11,祝日シート!A:A)) -> 1 | I62: 0.0069444444 | J62: OA端末関連 | K62: 顧客部 | M62: 池田 | N62: 低 | O62: 完了 | P62: OA端末のログイン時のエラー。画面が黒くなりマウスカーソル以外見えなくなる。 | Q62: Ctrl＋Alt＋Deleteキーでサインアウトし再度ログインすると正常動作でログインできるようになるので解消。Windows11 24H2の障害か？ FMVで多発する。
B63: ="No"&ROW()-3 -> No60 | C63: =IFERROR(IF(G63<>"",TEXT(G63,"yyyymm"),""),"") -> 202505 | D63: 要望 | E63: 坂本 | F63: 45784.385 | G63: 45784.427 | H63: =IF(F63="", "", NETWORKDAYS.INTL(F63, G63, 11,祝日シート!A:A)) -> 1 | I63: 0.041666667 | J63: 業務運用 | K63: 営業管理部 | M63: 岡村 | N63: 中 | O63: 完了 | P63: 在庫管理課）栗林さんのOA基幹ファイル移動用アカウント新規設定 | Q63: SKYSEA管理サーバにアカウント追加、ユーザーへの利用案内
B64: ="No"&ROW()-3 -> No61 | C64: =IFERROR(IF(G64<>"",TEXT(G64,"yyyymm"),""),"") -> 202505 | D64: 要望 | E64: 坂本 | F64: 45784.385 | G64: 45784.427 | H64: =IF(F64="", "", NETWORKDAYS.INTL(F64, G64, 11,祝日シート!A:A)) -> 1 | I64: 0.041666667 | J64: 業務運用 | K64: 顧客部 | M64: 岡元 | N64: 中 | O64: 完了 | P64: サービス課）松田さんのOA基幹ファイル移動用アカウント新規設定 | Q64: SKYSEA管理サーバにアカウント追加、ユーザーへの利用案内
B65: ="No"&ROW()-3 -> No62 | C65: =IFERROR(IF(G65<>"",TEXT(G65,"yyyymm"),""),"") -> 202505 | D65: 要望 | E65: 坂本 | F65: 45784.51 | G65: 45784.514 | H65: =IF(F65="", "", NETWORKDAYS.INTL(F65, G65, 11,祝日シート!A:A)) -> 1 | I65: 0.0034722222 | J65: 業務運用 | K65: 営業部 | M65: 深澤 | N65: 中 | O65: 完了 | P65: 直送品出荷指示 | Q65: 既定手順で対応済
... B88: ="No"&ROW()-3 -> No85 | C88: =IFERROR(IF(G88<>"",TEXT(G88,"yyyymm"),""),"") -> 202505 | D88: 要望 | E88: 伊藤 | F88: 45792.583 | G88: 45792.597 | H88: =IF(F88="", "", NETWORKDAYS.INTL(F88, G88, 11,祝日シート!A:A)) -> 1 | I88: 0.013888889 | J88: OA端末関連 | K88: 社長 | M88: 尾島社長 | N88: 低 | O88: 完了 | P88: マーケティング部が使用しているチャート作成ソフトの代替になるような簡単な操作のものがないか質問。 | Q88: ひとまず今のものに変わる簡単な操作のものがなく、様子見。引き続き調査。
B89: ="No"&ROW()-3 -> No86 | C89: =IFERROR(IF(G89<>"",TEXT(G89,"yyyymm"),""),"") -> 202505 | D89: 要望 | E89: 伊藤 | F89: 45792.625 | G89: 45792.708 | H89: =IF(F89="", "", NETWORKDAYS.INTL(F89, G89, 11,祝日シート!A:A)) -> 1 | I89: =#REF!-#REF! -> #REF! | J89: 基幹端末関連 | K89: 物流部 | M89: 山中 | N89: 低 | O89: 完了 | P89: 川口3階にあるプリンターを基幹端末にNW接続したい。 EPSONPX105 | Q89: 接続方法の確認。ドライバーの準備、IPアドレスの払い出しなど。月曜日に実施。 Forestwayで購入のLANケーブルが届いてからの作業を実施。→希望のLANケーブルが納品がまだ。 →納品されたので完了済み。
B90: ="No"&ROW()-3 -> No87 | C90: =IFERROR(IF(G90<>"",TEXT(G90,"yyyymm"),""),"") -> 202505 | D90: 要望 | E90: 伊藤 | F90: 45793.375 | G90: 45793.667 | H90: =IF(F90="", "", NETWORKDAYS.INTL(F90, G90, 11,祝日シート!A:A)) -> 1 | I90: 0.083333333 | J90: OA端末関連 | K90: 商品部 | M90: 成川 | N90: 低 | O90: 完了 | P90: Google Cheromeの設定がデスクトップの時のものにそろえたい。 | Q90: 完全に本人の要望のため協力はしたが自分で調査させて残りは本人に対応させる。
B91: ="No"&ROW()-3 -> No88 | C91: =IFERROR(IF(G91<>"",TEXT(G91,"yyyymm"),""),"") -> 202505 | D91: 要望 | E91: 佐々嶌 | F91: 45793.389 | G91: 45793.399 | H91: =IF(F91="", "", NETWORKDAYS.INTL(F91, G91, 11,祝日シート!A:A)) -> 1 | I91: 0.010416667 | J91: 基幹端末関連 | K91: 営業管理部 | M91: 大澤 | N91: 低 | O91: 完了 | P91: インプロのアドミニストレーターバージョンをインストールしたい。 | Q91: インストールしました。
B92: ="No"&ROW()-3 -> No89 | C92: =IFERROR(IF(G92<>"",TEXT(G92,"yyyymm"),""),"") -> 202505 | D92: 障害 | E92: 佐々嶌 | F92: 45793.401 | G92: 45793.403 | H92: =IF(F92="", "", NETWORKDAYS.INTL(F92, G92, 11,祝日シート!A:A)) -> 1 | I92: 0.0034722222 | J92: OA端末関連 | K92: 営業管理部 | M92: 三縞 | N92: 低 | O92: 完了 | P92: モニタが映らなくなった。 | Q92: 電源が抜けてました。
B93: ="No"&ROW()-3 -> No90 | C93: =IFERROR(IF(G93<>"",TEXT(G93,"yyyymm"),""),"") -> 202505 | D93: 課題 | E93: 伊藤 | F93: 45793.458 | G93: 45793.479 | H93: =IF(F93="", "", NETWORKDAYS.INTL(F93, G93, 11,祝日シート!A:A)) -> 1 | I93: 0.020833333 | J93: 総務関連 | K93: 管理部 | M93: 坂田 | N93: 中 | O93: 完了 | P93: コールセンター年間スケジュール登録による留守電のCTIへの設定の依頼調整。 | Q93: 見積もり取得、登録スケジュールの伝達。スケジュールの確定。5/21 10：00 メール・電話対応。
B94: ="No"&ROW()-3 -> No91 | C94: =IFERROR(IF(G94<>"",TEXT(G94,"yyyymm"),""),"") -> 202505 | D94: 要望 | E94: 坂本 | F94: 45793.469 | G94: 45793.479 | H94: =IF(F94="", "", NETWORKDAYS.INTL(F94, G94, 11,祝日シート!A:A)) -> 1 | I94: 0.0069444444 | J94: 業務運用 | K94: 顧客部 | M94: 北澤 | N94: 中 | O94: 完了 | P94: 在庫引き当て | Q94: 既定手順で対応済
B95: ="No"&ROW()-3 -> No92 | C95: =IFERROR(IF(G95<>"",TEXT(G95,"yyyymm"),""),"") -> 202505 | D95: 要望 | E95: 坂本 | F95: 45793.483 | G95: 45793.49 | H95: =IF(F95="", "", NETWORKDAYS.INTL(F95, G95, 11,祝日シート!A:A)) -> 1 | I95: 0.0034722222 | J95: 業務運用 | K95: 営業部 | M95: 佐藤 | N95: 中 | O95: 完了 | P95: 出荷予定日変更 | Q95: 既定手順で対応済
B96: ="No"&ROW()-3 -> No93 | C96: =IFERROR(IF(G96<>"",TEXT(G96,"yyyymm"),""),"") -> 202505 | D96: 要望 | E96: 坂本 | F96: 45793.552 | G96: 45793.559 | H96: =IF(F96="", "", NETWORKDAYS.INTL(F96, G96, 11,祝日シート!A:A)) -> 1 | I96: 0.0069444444 | J96: 業務運用 | K96: 営業部 | M96: 見形 | N96: 中 | O96: 完了 | P96: 着日変更、出荷指示依頼 | Q96: 直送品の着日変更可否を下村さんに確認し、対応いただいた
B97: ="No"&ROW()-3 -> No94 | C97: =IFERROR(IF(G97<>"",TEXT(G97,"yyyymm"),""),"") -> 202505 | D97: 支援 | E97: 佐々嶌 | F97: 45794.528 | G97: 45794.549 | H97: =IF(F97="", "", NETWORKDAYS.INTL(F97, G97, 11,祝日シート!A:A)) -> 1 | I97: 0.020833333 | J97: 配送 | K97: 川口配送センター | M97: 小林 | N97: 高 | O97: 完了 | P97: 新砂午後便の配車確定が定時に間に合わなかった。 | Q97: 自動配車を停止して、配車できる状態に変更。 その後確定してもらって、自動配車状態へ移行させた。
B98: ="No"&ROW()-3 -> No95 | C98: =IFERROR(IF(G98<>"",TEXT(G98,"yyyymm"),""),"") -> 202505 | D98: 要望 | E98: 坂本 | F98: 45796.413 | G98: 45796.42 | H98: =IF(F98="", "", NETWORKDAYS.INTL(F98, G98, 11,祝日シート!A:A)) -> 1 | I98: 0.0069444444 | J98: 業務運用 | K98: 顧客部 | M98: 久楽 | N98: 中 | O98: 完了 | P98: 在庫品の出荷指示依頼 | Q98: 在庫品の対応は手順不明のため、下村さんへ連絡。対応中に自動出荷指示がかかった。
B99: ="No"&ROW()-3 -> No96 | C99: =IFERROR(IF(G99<>"",TEXT(G99,"yyyymm"),""),"") -> 202505 | D99: 要望 | E99: 坂本 | F99: 45796.458 | G99: 45796.465 | H99: =IF(F99="", "", NETWORKDAYS.INTL(F99, G99, 11,祝日シート!A:A)) -> 1 | I99: 0.0069444444 | J99: 業務運用 | K99: 営業管理部 | M99: 三縞 | N99: 中 | O99: 完了 | P99: 混載設定追加 | Q99: 既定手順で対応済
B100: ="No"&ROW()-3 -> No97 | C100: =IFERROR(IF(G100<>"",TEXT(G100,"yyyymm"),""),"") -> 202505 | D100: 障害 | E100: 佐々嶌 坂本 伊藤 | F100: 45796.604 | G100: 45796.646 | H100: =IF(F100="", "", NETWORKDAYS.INTL(F100, G100, 11,祝日シート!A:A)) -> 1 | I100: 0.041666667 | J100: 基幹端末関連 | K100: 顧客部 | M100: 齋藤 | N100: 中 | O100: 完了 | P100: SCAWの得意先メモ表示で、管理番号入力後にEnterキーを押しても表示されない。他のアプリケーションや、SCAWの他の画面では正常に作動する。 | Q100: KVM切替機の不具合。接続ケーブル挿抜により解消。
B101: ="No"&ROW()-3 -> No98 | C101: =IFERROR(IF(G101<>"",TEXT(G101,"yyyymm"),""),"") -> 202505 | D101: 問合せ | E101: 佐々嶌 | F101: 45796.67 | G101: 45796.674 | H101: =IF(F101="", "", NETWORKDAYS.INTL(F101, G101, 11,祝日シート!A:A)) -> 1 | I101: 0.0069444444 | J101: OA端末関連 | K101: 管理部 | M101: 上村 | N101: 低 | O101: 完了 | P101: エクセルを開くとエラーが出ることがある。 閉じれば使えるが、対処方法があれば教えて欲しい。 | Q101: https://qiita.com/misty299/items/07700bee14499222d814 「C:\Users\FMV\AppData\Local\Packages\Microsoft.AAD.BrokerPlugin_cw5n1h2txyewy」内のファイルを削除、MS365アカウントで再ログイン
... B103: ="No"&ROW()-3 -> No100 | C103: =IFERROR(IF(G103<>"",TEXT(G103,"yyyymm"),""),"") -> 202505 | D103: 要望 | E103: 坂本 | F103: 45798.406 | G103: 45798.479 | H103: =IF(F103="", "", NETWORKDAYS.INTL(F103, G103, 11,祝日シート!A:A)) -> 1 | I103: 0.0069444444 | J103: 業務運用 | K103: 営業管理部 | M103: 三縞 | N103: 中 | O103: 完了 | P103: 混載設定追加 | Q103: 既定手順で対応済
B104: ="No"&ROW()-3 -> No101 | C104: =IFERROR(IF(G104<>"",TEXT(G104,"yyyymm"),""),"") -> 202505 | D104: 課題 | E104: 伊藤 | F104: 45798.417 | G104: 45798.431 | H104: =IF(F104="", "", NETWORKDAYS.INTL(F104, G104, 11,祝日シート!A:A)) -> 1 | I104: 0.013888889 | J104: 総務関連 | N104: 低 | O104: 完了 | P104: LANケーブル、マウスなどのシステムに関わる備品のForestway での購入。 | Q104: 既定手順で対応済
B105: ="No"&ROW()-3 -> No102 | C105: =IFERROR(IF(G105<>"",TEXT(G105,"yyyymm"),""),"") -> 202505 | D105: 要望 | E105: 坂本 | F105: 45798.458 | G105: 45791.462 | H105: =IF(F105="", "", NETWORKDAYS.INTL(F105, G105, 11,祝日シート!A:A)) -> -7 | I105: 0.0034722222 | J105: 業務運用 | K105: 営業部 | M105: 見形 | N105: 中 | O105: 完了 | P105: 直送品出荷指示 | Q105: 既定手順で対応済
B106: ="No"&ROW()-3 -> No103 | C106: =IFERROR(IF(G106<>"",TEXT(G106,"yyyymm"),""),"") -> 202505 | D106: 課題 | E106: 伊藤 | F106: 45798.729 | G106: 45798.771 | H106: =IF(F106="", "", NETWORKDAYS.INTL(F106, G106, 11,祝日シート!A:A)) -> 1 | I106: 0.0625 | J106: 業務運用 | K106: システム部 | N106: 高 | O106: 完了 | P106: EDI端末のバックアップ制作。5/21HDDコピー。起動確認。LANアダプタ購入。 | Q106: ひとまずコピー＆HDDの動作は確認。この後、PCを完全に予備用のものにして、LANアダプタの到着後に、サーバー室設置。福岡に引き渡してチェックをしてもらう予定。 →タスクスケジューラーの内容を改めて確認して、NWに接続してOKになってから。
B107: ="No"&ROW()-3 -> No104 | C107: =IFERROR(IF(G107<>"",TEXT(G107,"yyyymm"),""),"") -> 202505 | D107: 要望 | E107: 坂本 | F107: 45799.434 | G107: 45799.444 | H107: =IF(F107="", "", NETWORKDAYS.INTL(F107, G107, 11,祝日シート!A:A)) -> 1 | I107: 0.010416667 | J107: 業務運用 | K107: 顧客部 | M107: 池田 | N107: 中 | O107: 完了 | P107: 在庫引き当て | Q107: 既定手順で対応済
B108: ="No"&ROW()-3 -> No105 | C108: =IFERROR(IF(G108<>"",TEXT(G108,"yyyymm"),""),"") -> 202505 | D108: 要望 | E108: 坂本 | F108: 45799.444 | G108: 45799.448 | H108: =IF(F108="", "", NETWORKDAYS.INTL(F108, G108, 11,祝日シート!A:A)) -> 1 | I108: 0.0034722222 | J108: 業務運用 | K108: 営業部 | M108: 佐藤 | N108: 中 | O108: 完了 | P108: 出荷予定日変更 | Q108: 既定手順で対応済
B109: ="No"&ROW()-3 -> No106 | C109: =IFERROR(IF(G109<>"",TEXT(G109,"yyyymm"),""),"") -> 202505 | D109: 要望 | E109: 坂本 | F109: 45800.469 | G109: 45800.583 | H109: =IF(F109="", "", NETWORKDAYS.INTL(F109, G109, 11,祝日シート!A:A)) -> 1 | I109: 0.020833333 | J109: OA端末関連 | K109: 顧客部 | M109: 村本 | N109: 中 | O109: 完了 | P109: 端末起動時に毎回カーソルのみの画面表示となる | Q109: グラフィックドライバとBIOSを更新した。依頼者不在のため様子見。
B110: ="No"&ROW()-3 -> No107 | C110: =IFERROR(IF(G110<>"",TEXT(G110,"yyyymm"),""),"") -> 202505 | D110: 要望 | E110: 坂本 | F110: 45800.479 | G110: 45800.483 | H110: =IF(F110="", "", NETWORKDAYS.INTL(F110, G110, 11,祝日シート!A:A)) -> 1 | I110: 0.0034722222 | J110: 業務運用 | K110: 営業部 | M110: 佐藤 | N110: 中 | O110: 完了 | P110: 出荷予定日変更 | Q110: 既定手順で対応済
B111: ="No"&ROW()-3 -> No108 | C111: =IFERROR(IF(G111<>"",TEXT(G111,"yyyymm"),""),"") -> 202505 | D111: 要望 | E111: 坂本 | F111: 45800.646 | G111: 45800.66 | H111: =IF(F111="", "", NETWORKDAYS.INTL(F111, G111, 11,祝日シート!A:A)) -> 1 | I111: 0.0069444444 | J111: 業務運用 | K111: 営業部 | M111: 佐藤 | N111: 高 | O111: 完了 | P111: 出荷予定日変更（至急） | Q111: 既定手順で対応済
B112: ="No"&ROW()-3 -> No109 | C112: =IFERROR(IF(G112<>"",TEXT(G112,"yyyymm"),""),"") -> 202505 | D112: 要望 | E112: 坂本 | F112: 45804.375 | G112: 45805.417 | H112: =IF(F112="", "", NETWORKDAYS.INTL(F112, G112, 11,祝日シート!A:A)) -> 2 | I112: 0.0625 | J112: その他 | K112: マーケティング部 | M112: 藤田 | N112: 低 | O112: 完了 | P112: マーケティング部のBI分析でRを使用するが、Shiny(Rを利用したWebアプリパッケージ)の機能更新版が、一部動作しない。（analysis_1が起動しませんでした、というメッセージ） | Q112: 分析ファイルの内容を、詳細ログが出力できるよう修正して、その結果をChatAIで分析。分析結果から更にコードを修正（タイムアウト値の調整、viewer関数の修正）して正常動作を確認。
B113: ="No"&ROW()-3 -> No110 | C113: =IFERROR(IF(G113<>"",TEXT(G113,"yyyymm"),""),"") -> 202505 | D113: 要望 | E113: 坂本 | F113: 45804.396 | G113: 45804.399 | H113: =IF(F113="", "", NETWORKDAYS.INTL(F113, G113, 11,祝日シート!A:A)) -> 1 | I113: 0.0034722222 | J113: 業務運用 | K113: 顧客部 | M113: 木村 | N113: 中 | O113: 完了 | P113: 直送品出荷指示 | Q113: 既定手順で対応済
B114: ="No"&ROW()-3 -> No111 | C114: =IFERROR(IF(G114<>"",TEXT(G114,"yyyymm"),""),"") -> 202505 | D114: 課題 | E114: 坂本 | F114: 45804.406 | G114: 45804.413 | H114: =IF(F114="", "", NETWORKDAYS.INTL(F114, G114, 11,祝日シート!A:A)) -> 1 | I114: 0.0069444444 | J114: SCAW関連 | K114: 営業部 | M114: 見形 | N114: 中 | O114: 完了 | P114: 売上伝票入力メニューで、確定日付を入力する際に権限不足のメッセージが表示されるので解消したい。対象は見形、佐藤の割当端末。 | Q114: 下村さんに対応依頼
B115: ="No"&ROW()-3 -> No112 | C115: =IFERROR(IF(G115<>"",TEXT(G115,"yyyymm"),""),"") -> 202505 | D115: 障害 | E115: 坂本 | F115: 45804.417 | G115: 45804.583 | H115: =IF(F115="", "", NETWORKDAYS.INTL(F115, G115, 11,祝日シート!A:A)) -> 1 | I115: 0.010416667 | J115: 基幹端末関連 | K115: 顧客部 | M115: 林田 | N115: 高 | O115: 完了 | P115: 特定端末で、CTIシステムへのログインに失敗する。 | Q115: 下村さんに確認依頼。本端末に割当された内線番号が、別の端末に割当されているため、ログイン不可。こちらの対応としては無し。
B116: ="No"&ROW()-3 -> No113 | C116: =IFERROR(IF(G116<>"",TEXT(G116,"yyyymm"),""),"") -> 202505 | D116: 要望 | E116: 坂本 | F116: 45804.427 | G116: 45804.431 | H116: =IF(F116="", "", NETWORKDAYS.INTL(F116, G116, 11,祝日シート!A:A)) -> 1 | I116: 0.0034722222 | J116: OA端末関連 | K116: 管理部 | M116: 和田 | N116: 低 | O116: 完了 | P116: 管理部の共有端末にリモートデスクトップしたいが、ユーザー/パスワードが不明 | Q116: FMV/パスワード無しで接続可能であることを連絡
B117: ="No"&ROW()-3 -> No114 | C117: =IFERROR(IF(G117<>"",TEXT(G117,"yyyymm"),""),"") -> 202505 | D117: 課題 | E117: 坂本 | F117: 45804.438 | G117: 45804.667 | H117: =IF(F117="", "", NETWORKDAYS.INTL(F117, G117, 11,祝日シート!A:A)) -> 1 | I117: 0.020833333 | J117: OA端末関連 | K117: マーケティング部 | M117: 北山 | N117: 中 | O117: 完了 | P117: Excelで数十万行を扱う際に、フリーズする（メモリ不足？）動作が見られる。相川さんの端末では問題なく動作する。 | Q117: 北山さんPCと相川さんPCを比較すると、前者の方はWindows10でスペックも高い。取り急ぎOfficeの修復を実行して、経過観察とする。
B118: ="No"&ROW()-3 -> No115 | C118: =IFERROR(IF(G118<>"",TEXT(G118,"yyyymm"),""),"") -> 202505 | D118: 問合せ | E118: 坂本 | F118: 45804.479 | G118: 45804.542 | H118: =IF(F118="", "", NETWORKDAYS.INTL(F118, G118, 11,祝日シート!A:A)) -> 1 | I118: 0.0069444444 | J118: 名刺 | K118: 顧客部 | M118: 村本 | N118: 中 | O118: 完了 | P118: 一部の名刺が印刷出力されていないように思われる。再印刷で対応したが、システムで印刷履歴が確認可能か。 | Q118: 印刷は完了していたが、印刷物を紛失していたことが判明。対処なし。
... B132: ="No"&ROW()-3 -> No129 | C132: =IFERROR(IF(G132<>"",TEXT(G132,"yyyymm"),""),"") -> 202505 | D132: 要望 | E132: 坂本 佐々嶌 | F132: 45807.375 | G132: 45807.715 | H132: =IF(F132="", "", NETWORKDAYS.INTL(F132, G132, 11,祝日シート!A:A)) -> 1 | I132: 0.041666667 | J132: 業務運用 | K132: 営業管理部 | M132: 小幡 | N132: 高 | O132: 完了 | P132: VD変更、仕入先変更 | Q132: 既定手順で対応済
B133: ="No"&ROW()-3 -> No130 | C133: =IFERROR(IF(G133<>"",TEXT(G133,"yyyymm"),""),"") -> 202506 | D133: 課題 | E133: 佐々嶌 | F133: 45809.375 | G133: 45809.75 | H133: =IF(F133="", "", NETWORKDAYS.INTL(F133, G133, 11,祝日シート!A:A)) -> 0 | I133: 0.33333333 | J133: 業務運用 | K133: 顧客部 | N133: 中 | O133: 完了 | P133: 停電時に稼働していてほしいPC端末がUPSに接続されていない。 | Q133: UPSがどのエリアに接続されているか確認。電源タップの接続のやり直しと、起動の確認作業を実施。
B134: ="No"&ROW()-3 -> No131 | C134: =IFERROR(IF(G134<>"",TEXT(G134,"yyyymm"),""),"") -> 202506 | D134: 課題 | E134: 坂本 | F134: 45809.375 | G134: 45809.75 | H134: =IF(F134="", "", NETWORKDAYS.INTL(F134, G134, 11,祝日シート!A:A)) -> 0 | I134: 0.33333333 | J134: 業務運用 | K134: 顧客部 | N134: 中 | O134: 完了 | P134: 停電時に稼働していてほしいPC端末がUPSに接続されていない。 | Q134: UPSがどのエリアに接続されているか確認。電源タップの接続のやり直しと、起動の確認作業を実施。
B135: ="No"&ROW()-3 -> No132 | C135: =IFERROR(IF(G135<>"",TEXT(G135,"yyyymm"),""),"") -> 202506 | D135: 課題 | E135: 伊藤 | F135: 45809.375 | G135: 45809.75 | H135: =IF(F135="", "", NETWORKDAYS.INTL(F135, G135, 11,祝日シート!A:A)) -> 0 | I135: 0.33333333 | J135: 業務運用 | K135: 顧客部 | N135: 中 | O135: 完了 | P135: 停電時に稼働していてほしいPC端末がUPSに接続されていない。 | Q135: UPSがどのエリアに接続されているか確認。電源タップの接続のやり直しと、起動の確認作業を実施。
B136: ="No"&ROW()-3 -> No133 | C136: =IFERROR(IF(G136<>"",TEXT(G136,"yyyymm"),""),"") -> 202506 | D136: 要望 | E136: 坂本 | F136: 45810.375 | G136: 45810.382 | H136: =IF(F136="", "", NETWORKDAYS.INTL(F136, G136, 11,祝日シート!A:A)) -> 1 | I136: 0.0069444444 | J136: OA端末関連 | K136: 営業管理部 | M136: 小幡 | N136: 低 | O136: 完了 | P136: セキュリティソフトのAvast!が無料ライセンス期限の通知画面が表示される | Q136: 社内標準で使用しているセキュリティソフトではないため、アンインストールを実施
B137: ="No"&ROW()-3 -> No134 | C137: =IFERROR(IF(G137<>"",TEXT(G137,"yyyymm"),""),"") -> 202506 | D137: 障害 | E137: 佐々嶌 坂本 伊藤 | F137: 45810.412 | G137: 45810.427 | H137: =IF(F137="", "", NETWORKDAYS.INTL(F137, G137, 11,祝日シート!A:A)) -> 1 | I137: 0.025 | J137: サーバー | K137: 全体 | M137: 北澤 | N137: 高 | O137: 完了 | P137: SCAW画面が固まって動かないと連絡あり。 | Q137: 下村さんに電話。 SCAWDBサービスが落ちてしまっていた模様。 Forestway、ココデカウも接続不可。物流にも影響あり。 DBサーバーを再起動して復旧。 原因はオラクル統計情報を取得するテーブルの表領域が枯渇していた為？
B138: ="No"&ROW()-3 -> No135 | C138: =IFERROR(IF(G138<>"",TEXT(G138,"yyyymm"),""),"") -> 202506 | D138: 要望 | E138: 伊藤 | F138: 45810.417 | G138: 45810.427 | H138: =IF(F138="", "", NETWORKDAYS.INTL(F138, G138, 11,祝日シート!A:A)) -> 1 | I138: 0.010416667 | J138: OA端末関連 | K138: 営業部 | M138: 青木 | N138: 低 | O138: 完了 | P138: 切替器の切り替えができない。 | Q138: 切替器のホットキー再設定。キーボードもCtrlキーが押しづらく、キーボードの劣化があるので交換。
B139: ="No"&ROW()-3 -> No136 | C139: =IFERROR(IF(G139<>"",TEXT(G139,"yyyymm"),""),"") -> 202506 | D139: 障害 | E139: 坂本 | F139: 45810.438 | G139: 45810.458 | H139: =IF(F139="", "", NETWORKDAYS.INTL(F139, G139, 11,祝日シート!A:A)) -> 1 | I139: 0.010416667 | J139: 名刺 | K139: 顧客部 | M139: 村本 | N139: 中 | O139: 完了 | P139: 名刺編集の「コピーして新規作成」処理が実行不可 | Q139: 下村さんにエスカレーション。基幹DB障害発生検知後から10:40頃まで、FWS3⇒基幹へアクセスしないよう設定変更していた影響とのこと。
B140: ="No"&ROW()-3 -> No137 | C140: =IFERROR(IF(G140<>"",TEXT(G140,"yyyymm"),""),"") -> 202506 | D140: 障害 | E140: 佐々嶌 | F140: 45810.444 | G140: 45810.465 | H140: =IF(F140="", "", NETWORKDAYS.INTL(F140, G140, 11,祝日シート!A:A)) -> 1 | I140: 0.020833333 | J140: 配送 | K140: 川口配送センター | M140: 中澤 | N140: 低 | O140: 完了 | P140: 配送リスト（インプロ）が表示されなくなってしまった。 | Q140: プリンター設定がおかしくなっていたので正しく設定することで対応できた。7/4（金）再発。通常使用するプリンタをコニカミノルタにしてScawを再起動して対応。浅見PCの共有が邪魔してる可能性があり共有ドライバ削除。再発しないか確認を継続してもらう。
B141: ="No"&ROW()-3 -> No138 | C141: =IFERROR(IF(G141<>"",TEXT(G141,"yyyymm"),""),"") -> 202506 | D141: 要望 | E141: 坂本 | F141: 45810.542 | G141: 45810.559 | H141: =IF(F141="", "", NETWORKDAYS.INTL(F141, G141, 11,祝日シート!A:A)) -> 1 | I141: 0.0069444444 | J141: 業務運用 | K141: 営業管理部 | M141: 田中 | N141: 中 | O141: 完了 | P141: 仕入先登録 | Q141: 既定手順で対応済
B142: ="No"&ROW()-3 -> No139 | C142: =IFERROR(IF(G142<>"",TEXT(G142,"yyyymm"),""),"") -> 202506 | D142: 要望 | E142: 坂本 | F142: 45810.583 | G142: 45810.597 | H142: =IF(F142="", "", NETWORKDAYS.INTL(F142, G142, 11,祝日シート!A:A)) -> 1 | I142: 0.013888889 | J142: 業務運用 | K142: 顧客部 | M142: 矢ヶ崎 | N142: 中 | O142: 完了 | P142: 在庫引き当て | Q142: 既定手順で対応済
...

Sheet 社内機器・ソフト・システムの保守 - 作業内容管理・進捗
B1: システム運営課 社内機器・ソフト・システムの保守 - 作業内容管理・進捗
B3: No. | C3: 課題件名 | D3: 背景 | E3: 対応内容 | F3: 期限 | G3: 状況 | H3: 備考 | I3: 進捗
B4: =ROW()-3 -> 1 | C4: USB使用廃止と中継サーバー方式への完全移行 （USB回収、USBポート無効化、データ移行手順の統一） | D4: 会社全体で複数部署がUSBでデータ移動しており、工数・時間・セキュリティリスクが高い。 中継サーバー方式へ移行済みだが、各部署で所有していたUSBは未回収のため、継続利用の可能性がある。 | E4: 〇中継サーバー方式の標準化・完全移行 ・中継サーバー上で指定フォルダへの投入をトリガに自動転送するPythonプログラムを本番運用。 ・サーバー側にウイルス対策ソフトを導入済みで、投入ファイルのリアルタイムスキャンを有効化（従来のUSB全体スキャン運用と同等のセキュリティ水準を維持）。 ・接続ユーザーを管理し、パスワードは月1で定期変更。不要アカウントは都度無効化。 ・転送ログ、ファイルバックアップ機能あり。 〇USB回収 ・各部署で使用していたUSBの返却を依頼し、回収保管済み。 〇USBポート無効化 ・クライアント管理ツールSkySeaを用いて、システム統括部所属端末を除いて、USBストレージ含む外部メディアの接続を無効化。 ・恒久使用する外部メディアは、SkySeaに登録管理した上で接続を許可する。 ・一時使用する外部メディアは、使用期間を設定した上でSkySeaで一時的に接続を許可する。 | F4: 45777 | G4: 完了 | H4: ・各部署で所有していたUSBメモリの総数は不明だが、届出がない外部メディアはOA/基幹の両端末で一切使用できないため、セキュリティリスクは低いと考える | I4: ・毎月メンテナンスを実施(利用者のパスワード変更、中継サーバへのセキュリティ更新プログラム適用、転送プログラムの再起動等) ・データ移行に関する質問は随時相談可能
B5: =ROW()-3 -> 2 | C5: UPS（無停電電源装置）配線整備 | D5: ・昨年8月の雷による停電（土曜日）発生時、UPS配線の不備により「端末は稼働するがモニターが起動しない」またはその逆の事象が発生し、一時的に業務へ支障が出た。 ・当時は稼働している端末に業務を寄せて対応したが、再発時の業務継続性に課題がある。 | E5: 作業内容：UPS配線の整備 （端末・モニターが同一系統でUPS保護下に入るよう配線見直し、ラベル整備、通電確認） 対象エリア：顧客部の島 事前依頼事項 机の下の整理：作業しやすいよう事前清掃をお願いします 机上の整理：机移動時の落下防止のため、向かい側の机との間に物を置かないでください 作業後対応：通電確認、簡易動作確認（端末・モニター）、不具合時はその場で復旧またはエスカレーション | F5: 実施日時：6月1日（日） | G5: 完了 | H5: 作業中は電源ケーブルの抜き差しを行います。作業開始前に保存・ログオフをお願いします。 | I5: 実施日時：6月1日（日） 配線見直し→ラベリング→通電・表示確認→記録（完了シール/チェックリスト） 全て完了済み。
B6: =ROW()-3 -> 3 | C6: 【セキュリティ対策】 社内端末のパスワード変更 | D6: 昨今のサイバーセキュリティ環境を鑑み、社内システムの安全性をより一層高めるため、 全社員のOA端末のパスワード変更をお願いすることになった。 | E6: 全社員にパスワード変更するよう社内メールで通知。 その際、パスワードを忘れて入れなくならないようシステム管理者ユーザーも作成。 〇新しいパスワードの要件 ・8文字以上の長さ ・英大文字（A〜Z）を1文字以上 ・英小文字（a〜z）を1文字以上 ・数字（0〜9）を1文字以上 ・特殊記号（!@#$%^&*など）を1文字以上 | F6: 45842 | G6: 完了 | H6: ユーザーがパスワードを変更したかどうかは判断できない。 | I6: 案内済み。 システム管理者ユーザーが入っていない端末はその都度作成済み。 パスワードを忘れたユーザーに関してはシステム管理者ユーザーで入り、パスワードを変更できます。
B7: =ROW()-3 -> 4 | C7: データベース操作ツールの移行 | D7: 現在、SQLツールとしてオブジェクトブラウザーを使用していますが、以下の問題がある： 1. バージョンとライセンスの問題 バージョン9、11、12が混在して使用されている バージョン9はライセンスが無制限ですが、 フルアクセスモードのためセキュリティリスクが存在する（ここが一番問題） バージョン11、12のリードオンリー版はセキュリティ面では安全ですが、ライセンス数が限られている 2. ライセンス不足 リードオンリー版のライセンス数が限られているため、全ユーザーに提供できない 今後ユーザー数が増加した場合、対応できない 3. 互換性の問題 新規購入可能な最新バージョンはWindows XPに対応していないため、基幹環境では利用できない 4. 新規ユーザー対応の課題 新しいメンバーがSQLを使いたい場合も、セキュリティ的に問題のあるバージョン9を使わざるを得ない状況 | E7: 今後SQLの導入が必要なユーザーについてはフリーソフトの「A5:SQL」を利用してもらう。 導入と簡単な利用方法の説明はシステム運営課で対応する。 | F7: - | G7: 進行中 | H7: SIOBと若干使い勝手が違うので、その都度システム運営課で対応する。 | I7: A5:SQL導入：３名 SIOB9利用者：３名
A8: . | B8: =ROW()-3 -> 5 | C8: Windows 10サポート終了対応 | D8: Microsoft社のWindows 10のサポートが2025年10月14日に終了予定。 セキュリティ更新が提供されなくなるため、Windows11へアップグレードの対応が必要。 | E8: SkySeaなどを使ってリモートで更新できるか試したが難しい。 ただし、通常なら複数回再起動を促される毎に再起動を手動でやらないといけないものを 一度起動したら最後まで再起動してWindows11までアップグレードできるバッチを作成できそうなので それを使って帰り際にバッチを起動して、翌朝にはWindows11にアップグレードが完了している、というような なるべく業務に支障がでない対応が可能になる予定。 | F8: 45944 | G8: 進行中 | H8: 残存14台につきまして、引き続き計画的な実施スケジュールに基づき、 順次更新を実施していく予定です。 特に共用端末等、利用状況やロケーションに配慮した対応が必要な端末については、関係者と調整のうえ適切なタイミングでの更新を進めていきます。 | I8: 【10/15更新】 93.14%完了 (残14台) システム統括部 19/22台 完了率 86.4%（残3台） マーケティング部 14/14台 完了率100% 営業管理部 21/22台 完了率95.5%（残1台） 営業部 12/12台 完了率100% 管理部 15/15台 完了率100% 顧客部 49/55台 完了率89.10% (残6台) 商品部 15/18台 完了率83.30%（残3台） 物流部 29/30台 完了率96.7%（残1台） 本社役員 5/5台 完了率100% 遊休端末 11/11台 完了率100%
A9: . | B9: =ROW()-3 -> 6 | C9: Office 2019サポート終了対応 | D9: Office 2019(OA端末80台)のサポートが2025年10月14日に終了予定。 セキュリティ更新が提供されなくなるため、アップグレードが必要。 | E9: Officeの更新(購入)が必要。 2019の後継ソフトはOffice2024だが、サポートが5年(2029年)なので月毎の費用を計算すると サブスクリプションであるOffice365とあまり変わらないのと、Office365は常に機能が更新され 人によってエクセルのバージョンが違うことによる弊害の心配もないのでOffice365の導入の決定となった。 (稟議決裁済み) 古い2019を削除して新しいWindows365を自動的にインストールできるバッチを作成済み。 各部署と連携して順次更新をしていく。 | F9: 45944 | G9: 完了 | I9: 【完了】Office2024買い切り版 or MS365の導入方針決め 【完了】MS365追加ライセンス数の精査 【完了】富士フィルムBIJへライセンス追加申請、管理サイト上での割当数確認 【完了】Office2019の削除、MS365のインストールの実行スクリプト作成、検証 【完了】対象端末インストール実行（88/88台 100%完了済み）
A10: . | B10: =ROW()-3 -> 7 | C10: OAネットワーク新回線敷設 | D10: 毎月第二火曜日の翌日（WindowsUpdate配信日）朝の時間帯にインターネット接続が遅延して業務影響がある。 現行のOAネットワーク回線はPPPoE接続方式のため混雑の影響を受けやすく、IPoE方式へ変更する。 | E10: 本社インターネット接続の主回線として新規NUROアクセススタンダードを契約する（10Mbps帯域保証） 主回線トラブル時の予備として現OCN回線を保持するが、予備へ切り替える際の運用上、プライベートIPアドレス（10.85.32.0/23）の使用が必須となるため、新回線開通に合わせて本社設置端末のIPアドレスを変更する。 また新回線で割当されるグローバルIPアドレスを確認して、IP制限を行っているサイト、サービスへ登録する | F10: 2025/12末 | G10: 完了 | I10: 【完了】 ～9月末 新回線申込、本社一部端末のIPアドレス変更 【完了】～10月末 本社全端末のIPアドレス変更(10/20～24)、回線工事事前調査(10/28) 【完了】～11月末 新回線のグローバルIPアドレスの確認、各種IP制限サイトへの登録 【完了】12月以降 本社NW作業実施、新OA回線利用開始
B11: =ROW()-3 -> 8 | C11: アーカイブソフトウェア「Lhaplus」の廃止と「7-Zip」の利用推進 | D11: 全社OA端末で利用されている「Lhaplus」は2017年で開発が停止しており、現在一部の圧縮方式で脆弱性が存在することが判明している。解凍時に文字化けが発生するなど機能的な問題もあり、代替ソフトウェアとして「7-Zip」への移行を推進する。 | E11: OA端末上で「Lhaplus」のインストール有無を調査して削除、「7-Zip」をインストールするツールを作成し、全社展開する。 | F11: 2025/12末 | G11: 完了
B12: 9 | C12: 自動封函機と物流サーバー間のデータ連携 | D12: 物流センターに導入される封函機、仕分け機稼働のため、物流サーバーと出荷実績、出荷指示の各データの受け渡しを行うネットワークを構築する | E12: ・封函機メーカー側で外部から機器動作状況の確認を行うため、インターネット接続環境構築する ・封函機側のネットワーク環境と当社基幹ネットワークを分離し、ネットワーク間にNASを 配置してSFTPプロトコルのみ許可する方式とする | F12: 46064 | G12: 進行中 | I12: ・外部ネットワーク接続は不要（問題発生時はメーカー側の駆けつけ対応） ・EXVへのネットワーク構築作業の発注が遅延したため、NASの代替とする 基幹PCを構築配置して、データ受け渡しを実行中 ・NASへの切り替えは、3/5に実施したが検証中にNASの不具合があり 調査中 ・３月中旬の調査の過程で不具合が解消、切替作業時に封函機メーカー側の立ち合いが必要なため、スケジュール調整中
B13: 10 | C13: 本社休憩室へのWi-Fi環境構築 | D13: 社長、信川専務の座談会から休憩室でWi-Fiが使用したいとの要望があり対応 | E13: モバイルルータを設置する案、業務用のOA予備回線を使用する案など検討したが、コスト面をクリアしたため、新たにOCN回線を契約して使用する | F13: - | G13: 完了 | I13: ・2025/11：当時案の相談あり、検討開始 ・2025/12：OA予備回線流用案を含めてEXVへ見積もり提出、合わせて東日本物流センターでも休憩室への導入を検討 ・2026/1：EXVへの発注、現地調査および工事日程調整開始 ・2026/2：回線工事完了、利用開始（東日本物流センターは見送り）
B14: 11 | C14: GoogleWorkspaceの導入支援 | D14: Geminiによる業務効率化推進、既存の全社コミュニケーションツール（メール、メッセージ、掲示板、ファイル共有）の見直し | E14: システム部としては以下を業務スコープとする ■システム対応 アカウント発行、データ移行設計、セキュリティ設定、 （既存システム（サイボウズ等）との併用設定） | F14: - | G14: 進行中 | H14: https://docs.google.com/spreadsheets/d/1hdokrHlTowNvE1OUsHEKj0O6p0VMtt4R1OhtIilolZc/edit?gid=1292048900#gid=1292048900 | I14: ・アカウント発行：利用対象ユーザーへのアカウント発行完了（4/13時点） ・データ移行設計：Gmailへのメールデータ移行方法を調査し対応中。サイボウズメッセージはエクスポート機能がないため、全件テキスト出力するツール（PythonによるWebページ操作）を開発試験中
B15: 12 | C15: 本社OAネットワークの機器・回線障害時の切替簡易化 | D15: No.7の関連。予備回線と本回線で個別のゲートウェイアドレスを持つ構成であったため、予備回線への切り替え時に既存の手順（LANケーブルの差替え）での運用とするための対応 | E15: ルータ設定を変更して統一のゲートウェイアドレスとし、ケーブル抜線結線による切替方式とした | F15: - | G15: 完了 | I15: ・3/18に切替作業を実施していたが、１本のケーブルの差替えで完了する構成に見直すため、3/25に再作業して完了。 ・作業後にOCNで払い出されるDNSアドレスを設定している端末がインターネット接続不可となる障害が発生。公開DNSサーバーである8.8.8.8や1.1.1.1を設定して対処完了
B16: 13 | C16: 従来のOA・基幹の各共有フォルダ内データのNASへの移行 | D16: OA側は共有元のMS02Y-Nサーバーの保守解約のため、基幹側は空き容量枯渇のため、既存の共有ファイルをNASへ移行する | E16: OA側：移行アナウンス後、サーバー上でフォルダ共有を解除する 基幹側：システム上必要なフォルダ以外をNASへ移行 | F16: 2026/3末 | G16: 進行中 | I16: ・4/1にOA共有フォルダの共有停止を行ったが、配送部の移行が未完了であったため共有停止は延期 ・順次基幹NASへの移行が進行。各部のショートカットファイルやツールの呼び出し先が共有フォルダに指定されているため、変更対応中
B17: 14 | C17: NTT東日本と保守契約しているネットワーク機器の更改対応 | D17: フォーレスト各拠点と取引先を接続するVPNルータについて、メーカーサポート切れにより、保守契約を一時解約したいとの申し出があり、機器更改した上で再度保守を依頼する | E17: 計12台の機器リプレイスと保守契約の見積もりを取得して発注および工事予定。 リプレイスは対象の拠点、取引先で一斉に実行するため、スケジュールの調整が必要。 | F17: ー | G17: 進行中 | I17: 見積算出にリプレイス作業の開始時間の提示が必要。関係部署と調整が必要。
B18: 15 | C18: Bizストレージファイルシェアの導入 | D18: 顧客、取引先とのファイル共有において、PASS付きZipファイルによるメール添付とパスワード通知という手段が慣習化しているが、誤送信など情報漏洩リスクがあり、クラウドサービスの利用でリスク低減を図る | E18: Bizストレージファイルシェアを導入して、原則メールへのファイル添付は禁止とする | F18: ー | G18: 完了
B19: 16 | C19: 北浦和データセンターの保守切れサーバーの撤去、旧FAXOCRサーバーのHDD増設および福岡システム開発室移送 | D19: 保守契約が終了しているサーバー6台について、将来的な新サーバーのラッキングスペースを確保するため撤去する。また旧FAXOCRサーバー2台および旧W-FL03サーバーは開発用サーバーとして転用する。 | E19: 旧FAXOCRサーバーは福岡システム開発室へ移送、新開発用サーバーとして構築中。 旧W-FL03サーバーは大宮本社のサーバーラックに配置して、Win2016評価版を導入し各種検証サーバーとして活用する | F19: ー | G19: 完了
B20: 17 | C20: WEBアプリケーションサーバー更改 | D20: 現行WEBアプリケーションサーバーのアクセス数増加対応、メモリーリークによる不定期シャットダウン解消に向け、サーバーリプレイスを行う。 | E20: リプレイスに伴い、以下を行う ・サーバーのハードウェア構成確認 ・WindowsServer設定シートの記載確認 ・北浦和データセンターのラッキングスペースの確保 ・既存ネットワークスイッチとの接続作業および暫定構成検討 ・ルーティングテーブル、NTP、SMB1.0無効化など追加設定 | F20: ー | G20: 進行中 | I20: 5/13サーバ搬入予定、それまでにネットワークスイッチへのLANケーブル接続を内製で対応予定
B21: 18 | C21: 新CTI対応 | D21: 現行のCTIシステムの交換機AspireUXが保守期限切れとなっており、新しい交換機と電話機にリプレイスする | E21: 下村部長、CTI構築ベンダーと連携して新電話機の内線番号設定や現場検証を進める | F21: ー | G21: 進行中 | I21: 新電話機の設定は完了。新CTI端末が準備出来次第、新交換機での業務試験を実施予定
B22: 19 | C22: EDION社員用・予備機PCキッティング | D22: EDION出向社員がGWSのポータルがノートPCで会議などで閲覧できないので ノートPCを支給してほしいとの要望。 | E22: 見積もり（使用方法に対して金額が高いので中古）・稟議・キッティング作業。 ７台購入し対応。（中古で購入だが１台が不具合あり。修理のために返送。戻り次第予備機として キッティングの予定。必要なEDION社員には配布したので一旦終了とする。 | F22: ー | G22: 完了 | H22: 中古の品質はイオシスのほうがAmazonより上。故障があったが 対応の柔軟性もイオシス。 個別に設定が複雑化しており、キッティングの基本部分は スクリプトで短縮できたが全体の時間は増加。６台16.5時間４日。
B23: 20 | C23: PCモニタ2台・LANケーブル、 スイッチングハブ購入 | D23: モニターは人員増加で2台をすぐ使用予定。LANケーブルは在庫がなくなったので追加購入。 窓際の重役席のHubがないので購入。 | E23: モニターは見積もり、稟議、EDIONクロスベンチャーズに発注。 LAN、ハブはForestwayで購入。 | F23: 46174 | G23: 完了 | H23: 入荷後、必要個所に配布、設置。
B24: 21 | C24: 商品部 梅森社員の基幹端末キッティング | D24: WindowsXPの在庫がないため在庫していたWin10のPCを使用し基幹端末を制作。 | E24: CTI導入の予定に合わせてVM-wareを使用した仮想化。マスタのvmdk化や設定を調査し、 仮想化での課題の抽出と手順化もかねて対応。 | F24: 46185 | G24: 完了 | H24: VM-wareなら設定が容易。HDD仕様、８GBメモリでもSCAWのみなら動作がそれほど重くない。ホスト起動後にゲストの自動起動と画面最大化もクリア。
B25: 22 | C25: 商品部商品管理課 野崎社員の基幹端末キッティング | D25: Windows11の環境下で基幹端末を作成し、ホスト側で基幹データをPythonを使用し処理したい。そのため仮想化した基幹端末を作成。 | E25: 工場出荷状態のWindows10端末から専用ISOファイルを作成しクリーンインストール（更新の時間を削減） そこからVM-Wareでの構築。問題抽出。 | F25: 46202 | G25: 完了 | H25: 引渡し済み。課題：ホスト側のOfficeソフトのオフラインインストール、VM用のデータ抽出の時間（300GBで8時間弱）、vmdkへの変換（1.5時間）など。また個別に問題点が出てくるものの対応が必要。抽出から付与までの期間のデータの差分解消方法の検討。
C26: 物流 浅野部長、三嶋部長社用スマホへの機種変更 | D26: GWS導入で外出、倉庫内にいるときに情報を確認するためにガラケーからスマホへの機種変更を希望。 | E26: Android端末2台の新規見積もりおよび納期情報の依頼。 | F26: 46213 | G26: 完了
C27: 福岡開発室 開発用モニター試験導入のための購入 | D27: 田中役員から開発現場で効率化を図るために購入の希望。 | E27: 福岡AI開発環境用として31インチ以上・高解像度モニターの提案・見積を依頼。EXV宮澤様に見積もり、社内稟議作成の代行、発注業務。 | F27: 46204 | G27: 完了
C28: 名刺印刷室UPSバッテリー購入 | D28: 5年経過のUPSバッテリーの寿命から通知が発されたため、交換に至る。 | E28: 名刺印刷室UPS バッテリー劣化でエラー。 EXV宮澤様に見積もり、Amazonと比較し、社内稟議。 Amzonで購入。交換済み。 | F28: 46206 | G28: 完了
C29: （GWS関連対応）EDION社員用PC購入、キッティング | D29: 亀澤社員、深澤社員、外山社員用OA端末購入の件。 管理部よりGWS導入で外出、会議で使用するためデスクトップPCから変更の要請のため。 | E29: イオシスで見積もり、稟議、購入後にキッティングし配布。（7/1～7/7） 外山社員はリカーズAKIBAに郵送処理。 | F29: 46211 | G29: 完了
C30: 福岡開発室 西島社員ガラケー貸与 | D30: 田中役員休職時に、緊急連絡を取れる体制構築のため。 | E30: 福岡（西島さん用）に在庫ガラケーを初期化し発送対応。チャットで福岡に連絡。 | F30: 46202.614 | G30: 完了
C31: 仮想基幹端末用Office2019運用 | D31: 基幹端末仮想化で社内で使用していないOffice2019で既存の2010より効率化が図れる可能性。ライセンスが余っているのでオフラインで使用、認証が可能か調査。 | E31: 仮想端末で使用するOffice 2019のKMSホストキーに関する問い合わせ。 オフラインインストーラーの作成を実施。 富士フィルム 仲居様 | F31: 46203.376 | G31: 進行中 | H31: 追加でライセンスの購入が必要。返信待ち。
C32: 社長室ミーティングスペース31.5インチPCモニター購入 | D32: 社長室ミーティングスペースで大型のモニターでPC画面を表示させて打ち合わせ等を行いたい。 | E32: 本社社長室で使用するモニター1台分の正式見積書作成依頼 EXV宮澤様に見積もり、発注業務。7/2～7/14 | F32: 46217.376 | G32: 進行中
C33: （GWS関連対応）役職者用PC購入、キッティング | D33: 管理部より野崎、北澤、岡本社員用中古OAノートPC購入の件で依頼。 GWS導入で外出、会議で使用するためデスクトップPCから変更の要請のため。 | E33: イオシスで見積もり、稟議、購入後にキッティングし配布。 | F33: 46217.376 | G33: 進行中 | H33: 7/14稟議書作成中
C34: 新入社員受け入れ対応 | D34: 7月派遣社員の受け入れ準備のため。 | E34: 7月中旬入社予定の派遣社員用端末のOffice365ライセンス追加依頼。 チャットで坂田部長に依頼。 | F34: 46216 | G34: 完了 | H34: 7/14 納品待ち
C35: 新入社員受け入れ対応 | D35: 7月派遣社員の受け入れ準備のため。 | E35: 7月中旬入社予定の派遣社員用、OA、基幹端末、備品の準備。 キッティングし一式そろえて設置の予定。 | F35: 46219 | G35: 進行中 | H35: 7/14 90％完了
C36: 組織変更による端末準備対応 | D36: 体制変更のため管理部からの依頼。 | E36: 管理部依頼の新規OA端末用ノートPCの見積もり、モニター3台の見積もり EXV宮澤様に見積もり、社内稟議作成の代行、発注業務。 | F36: 46219 | G36: 進行中 | H36: 7/14 見積り依頼済み
C37: （GWS関連対応）OA端末スペックアップ | D37: GWS導入でメモリ不足が顕著に発生するため管理部に提出用のメモリ増設計画の資料作成 | E37: SkySeaから８GBメモリ端末を抽出。価格調査、設置方法を明示。 | F37: 46219 | G37: 進行中 | H37: 提出待ち
A59: .

Sheet 2604変更前　ヘルプデスク - 作業内容管理・進捗
C1: システム運営課 ヘルプデスク - 作業内容管理・進捗
B3: No | C3: 1.分類 | D3: 2.担当者 | E3: 3.日付 | F3: 4.発生時刻 | G3: 5.終了時刻 | H3: 6.実作業時間 | I3: 7.終了予定日 | J3: 8.完了日付 | K3: 9.ジャンル | L3: 10.依頼部署 | M3: 11.依頼部署 | N3: 12.依頼主 | O3: 13重要度 | P3: 14.ステータス | Q3: 15.問題事象・作業内容 | R3: 15.対応内容
B4: ="No"&ROW()-3 -> No1 | C4: 障害 | D4: 伊藤 | E4: 45778 | F4: 0.375 | G4: 0.37847222 | H4: 0.0034722222 | I4: 45778 | J4: 45778 | K4: OA端末関連 | L4: 営業部 | N4: 佐藤 | O4: 低 | P4: 完了 | Q4: OA端末のログイン時のエラー。画面が黒くなりマウスカーソル以外見えなくなる。 | R4: Ctrl＋Alt＋Deleteキーでサインアウトし再度ログインすると正常動作でログインできるようになるので解消。Windows11 24H2の障害か？ FMVで多発する。
B5: ="No"&ROW()-3 -> No2 | C5: 障害 | D5: 伊藤 | E5: 45772 | F5: 0.33333333 | G5: 0.375 | H5: 0.16666667 | I5: 45778 | J5: 45778 | K5: OA端末関連 | L5: 物流部 | N5: 山中 | O5: 中 | P5: 完了 | Q5: 川口3階のアルバイト・パート社員打刻PCの不調、Freeeの打刻アプリの更新ができない。リモート接続できず本社に送り対応。 | R5: SSDの不良がありコピーし移植。BIOSなどの更新含め対応。管理部でFreeeの設定を行い発送。設置後にテストをしてもらい、完了。
B6: ="No"&ROW()-3 -> No3 | C6: 要望 | D6: 伊藤 | E6: 45778 | F6: 0.375 | G6: 0.38194444 | H6: 0.0069444444 | I6: 45778 | J6: 45778 | K6: 総務関連 | L6: 管理部 | N6: 関口 | O6: 低 | P6: 完了 | Q6: 新入社員 沖田さんのメールアカウントの作成と、サイボウズ への登録・確認。 | R6: 左記の内容
B7: ="No"&ROW()-3 -> No4 | C7: 障害 | D7: 伊藤 | E7: 45778 | F7: 0.47916667 | G7: 0.70486111 | H7: 0.03125 | I7: 45778 | J7: 45778 | K7: OA端末関連 | L7: 川口配送センター | N7: 中澤 | O7: 中 | P7: 完了 | Q7: 中澤さんOA端末 Win11に更新によるものでスキャンボックスに入る際に、 認証が必要となり使用できない。 | R7: 本社から配送センターの複合機に管理者ログイン。ボックス内の中澤アカウントにパスワードを設定しテスト。11からWindows資格情報にIP、ボックス番号、パスワード設定が必須。総務人事からのフォルダに資料を保管。
B8: ="No"&ROW()-3 -> No5 | C8: 要望 | D8: 坂本 | E8: 45778 | F8: 0.41666667 | G8: 0.625 | H8: 0.041666667 | I8: 45786 | J8: 45792 | K8: OA端末関連 | L8: 顧客部 | N8: 遠藤 | O8: 低 | P8: 完了 | Q8: オーダーメイドで使用する外付けHDDが認識不可 | R8: ①外付けHDDを接続する端末を、USBストレージの制限対象外とする ②外付けHDD自体を使用許可するメディアとしてSKYSEA登録して①を解除する
B9: ="No"&ROW()-3 -> No6 | C9: 障害 | D9: 坂本 | E9: 45778 | F9: 0.4375 | G9: 0.70833333 | I9: 45779 | K9: その他 | L9: 顧客部 | N9: 村本 | O9: 中 | P9: 完了 | Q9: 名刺端末でスキャンしたデータが名刺サーバ上(\\flbc01\MEISHI_LOGO\OUT)に存在せず、また見覚えのないデータが存在する | R9: 社内メールで福岡へ調査依頼 →名刺ロゴ抽出のプログラムが、動作中の状態に見えて一部機能に不具合が発生。プログラムを再起動して解消。
B10: ="No"&ROW()-3 -> No7 | C10: 支援 | D10: 伊藤 | E10: 45778 | F10: 0.70833333 | G10: 0.72222222 | H10: 0.013888889 | I10: 45778 | J10: 45778 | K10: 総務関連 | L10: 管理部 | N10: 坂田 | O10: 中 | P10: 完了 | Q10: Bizストレージ＆ファイルシェア 見積書＆申込書の申し込み・疑問点の確認のためNTTコールセンター担当者と電話。 | R10: 見積書・申込書はExelファイルでZipファイルでメールで受信予定。週明け。 担当：清水様 0120-950-138
B11: ="No"&ROW()-3 -> No8 | C11: 支援 | D11: 伊藤 | E11: 45778 | F11: 0.72222222 | G11: 0.72916667 | H11: 0.0069444444 | I11: 45778 | J11: 45778 | K11: その他 | L11: 営業管理部 | N11: 津田 | O11: 低 | P11: 完了 | Q11: iPad 業務用アプリケーション更新作業の手順の確認 | R11: Apple IDを入力し対応。2要素認証が管理部部長だった岡村さんに行くのでGWに修正し変更する予定。
B12: ="No"&ROW()-3 -> No9 | C12: 課題 | D12: 伊藤 | E12: 45778 | F12: 0.41666667 | G12: 0.4375 | H12: 0.020833333 | I12: 45778 | J12: 45778 | K12: その他 | L12: システム部 | N12: 下村 | O12: 低 | P12: 完了 | Q12: KPIや業績評価で必要な運営課の作業内容を入力するシートの作成（本シート） | R12: 作成完了。下村さんにパスを共有するメール。
B13: ="No"&ROW()-3 -> No10 | C13: 問合せ | D13: 佐々嶌 | E13: 45778 | F13: 0.72916667 | G13: 0.73611111 | H13: 0.0069444444 | I13: 45778 | J13: 45778 | K13: その他 | L13: 営業部 | N13: 見形 | O13: 中 | P13: 完了 | Q13: メモ番号:36065967の内容が自動的？に入っているが、メールが届いていない。メモ内容がメールと自動連携されているのでメールがあるはず、とのこと。 | R13: よくわからないので下村さんにお願いしました。
B14: ="No"&ROW()-3 -> No11 | C14: 問合せ | D14: 坂本 | E14: 45779 | F14: 0.59375 | G14: 0.60416667 | H14: 0.010416667 | I14: 45779 | J14: 45779 | K14: 基幹端末関連 | L14: 物流部 | N14: 浅野 | O14: 中 | P14: 完了 | Q14: 基幹データ移動の際、中継サーバに接続不可。 | R14: 128.128.5.6のみ疎通ができない状態。再起動後に状況を確認しようとしたが、浅野さんに端末制御が移ったため、メールで接続確認を依頼。
B15: ="No"&ROW()-3 -> No12 | C15: 要望 | D15: 坂本 | E15: 45779 | F15: 0.54166667 | G15: 0.55208333 | H15: 0.010416667 | I15: 45779 | J15: 45779 | K15: OA端末関連 | L15: 物流部 | N15: 名塚 | O15: 中 | P15: 完了 | Q15: OA端末192.176.5.11でUSBメモリの接続許可依頼 | R15: SKYSEAで接続許可対応
B16: ="No"&ROW()-3 -> No13 | C16: 支援 | D16: 佐々嶌 坂本 | E16: 45779 | F16: 0.79166667 | G16: 0.75 | H16: 0.33333333 | I16: 45786 | J16: 45786 | K16: 開発 | L16: 顧客部 | N16: 野尻 | O16: 中 | P16: 完了 | Q16: ライフル買い物コネクトで欠品商品を抽出するツールの仕様変更 | R16: 要望通り対応
B17: ="No"&ROW()-3 -> No14 | C17: 支援 | D17: 佐々嶌 | E17: 45784 | F17: 0.65625 | G17: 0.76041667 | H17: 0.10416667 | I17: 45784 | J17: 45784 | K17: その他 | L17: 商品部 | N17: 安形 | O17: 高 | P17: 完了 | Q17: エディオン財務部 配信用のエクセルの集計シートのデータが月毎のシートの合計と合わないので調査して修正してほしいとのこと。急ぎ。 | R17: 各月のシートのカテゴリが毎月変わっているので、集計シートは対象の全カテゴリを含めないと正しい値にならない。修正済み。
B18: ="No"&ROW()-3 -> No15 | C18: 障害 | D18: 伊藤 | E18: 45784 | F18: 0.375 | G18: 0.38194444 | H18: 0.0069444444 | I18: 45784 | J18: 45784 | K18: OA端末関連 | L18: 顧客部 | N18: 池田 | O18: 低 | P18: 完了 | Q18: OA端末のログイン時のエラー。画面が黒くなりマウスカーソル以外見えなくなる。 | R18: Ctrl＋Alt＋Deleteキーでサインアウトし再度ログインすると正常動作でログインできるようになるので解消。Windows11 24H2の障害か？ FMVで多発する。
B19: ="No"&ROW()-3 -> No16 | C19: 障害 | D19: 坂本 | E19: 45786 | F19: 0.35416667 | G19: 0.36111111 | H19: 0.0069444444 | I19: 45786 | J19: 45786 | K19: OA端末関連 | L19: 顧客部 | N19: 村本 | O19: 低 | P19: 完了 | Q19: OA端末のログイン時のエラー。画面が黒くなりマウスカーソル以外見えなくなる。 | R19: Ctrl＋Alt＋Deleteキーでサインアウトし再度ログインすると正常動作でログインできるようになるので解消。Windows11 24H2の障害か？ FMVで多発する。
B20: ="No"&ROW()-3 -> No17 | C20: 課題 | D20: 坂本 | E20: 45786 | F20: 0.35416667 | G20: 0.41666667 | H20: 0.041666667 | I20: 45786 | J20: 45786 | K20: 開発 | L20: 顧客部 | N20: 林田 | O20: 高 | P20: 完了 | Q20: 母の日ギフト商品の業務支援ツールで、社外モールにアップロードするデータに既定外のデータ項目が出力される | R20: ｄショッピング向けのCSVデータで各行末尾に空データが存在するため、削除する仕組みを追加。
B21: ="No"&ROW()-3 -> No18 | C21: 問合せ | D21: 佐々嶌 | E21: 45789 | F21: 0.43055556 | G21: 0.4375 | H21: 0.0069444444 | I21: 45789 | J21: 45789 | K21: OA端末関連 | L21: 物流部 | N21: 浅野 | O21: 中 | P21: 完了 | Q21: OAから基幹へのファイル転送に失敗する | R21: フォルダでの移動を実施したため、転送ができなかった。ファイル個別での転送を依頼。
... B46: ="No"&ROW()-3 -> No43 | C46: 要望 | D46: 伊藤 | E46: 45792 | F46: 0.58333333 | G46: 0.59722222 | H46: 0.013888889 | I46: 45792 | J46: 45792 | K46: OA端末関連 | L46: 社長 | N46: 尾島社長 | O46: 低 | P46: 完了 | Q46: マーケティング部が使用しているチャート作成ソフトの代替になるような簡単な操作のものがないか質問。 | R46: ひとまず今のものに変わる簡単な操作のものがなく、様子見。引き続き調査。
B47: ="No"&ROW()-3 -> No44 | C47: 要望 | D47: 伊藤 | E47: 45792 | F47: 0.625 | G47: 0.64583333 | H47: =G47-F47 -> 0.020833333 | K47: 基幹端末関連 | L47: 物流部 | N47: 山中 | O47: 低 | P47: 完了 | Q47: 川口3階にあるプリンターを基幹端末にNW接続したい。 EPSONPX105 | R47: 接続方法の確認。ドライバーの準備、IPアドレスの払い出しなど。月曜日に実施。 Forestwayで購入のLANケーブルが届いてからの作業を実施。→希望のLANケーブルが納品がまだ。 →納品されたので完了済み。
B48: ="No"&ROW()-3 -> No45 | C48: 要望 | D48: 佐々嶌 | E48: 45793 | F48: 0.38888889 | G48: 0.39930556 | H48: 0.010416667 | I48: 45793 | J48: 45793 | K48: 基幹端末関連 | L48: 営業管理部 | N48: 大澤 | O48: 低 | P48: 完了 | Q48: インプロのアドミニストレーターバージョンをインストールしたい。 | R48: インストールしました。
B49: ="No"&ROW()-3 -> No46 | C49: 障害 | D49: 佐々嶌 | E49: 45793 | F49: 0.40138889 | G49: 0.40277778 | H49: 0.0034722222 | I49: 45793 | J49: 45793 | K49: OA端末関連 | L49: 営業管理部 | N49: 三縞 | O49: 低 | P49: 完了 | Q49: モニタが映らなくなった。 | R49: 電源が抜けてました。
B50: ="No"&ROW()-3 -> No47 | C50: 要望 | D50: 坂本 | E50: 45793 | F50: 0.46875 | G50: 0.47916667 | H50: 0.0069444444 | I50: 45793 | J50: 45793 | K50: 業務運用 | L50: 顧客部 | N50: 北澤 | O50: 中 | P50: 完了 | Q50: 在庫引き当て | R50: 既定手順で対応済
B51: ="No"&ROW()-3 -> No48 | C51: 要望 | D51: 坂本 | E51: 45793 | F51: 0.48263889 | G51: 0.48958333 | H51: 0.0034722222 | I51: 45793 | J51: 45793 | K51: 業務運用 | L51: 営業部 | N51: 佐藤 | O51: 中 | P51: 完了 | Q51: 出荷予定日変更 | R51: 既定手順で対応済
B52: ="No"&ROW()-3 -> No49 | C52: 要望 | D52: 坂本 | E52: 45793 | F52: 0.55208333 | G52: 0.55902778 | H52: 0.0069444444 | I52: 45793 | J52: 45793 | K52: 業務運用 | L52: 営業部 | N52: 見形 | O52: 中 | P52: 完了 | Q52: 着日変更、出荷指示依頼 | R52: 直送品の着日変更可否を下村さんに確認し、対応いただいた
B53: ="No"&ROW()-3 -> No50 | C53: 支援 | D53: 佐々嶌 | E53: 45794 | F53: 0.52777778 | G53: 0.54861111 | H53: 0.020833333 | I53: 45794 | J53: 45794 | K53: 配送 | L53: 川口配送センター | N53: 小林 | O53: 高 | P53: 完了 | Q53: 新砂午後便の配車確定が定時に間に合わなかった。 | R53: 自動配車を停止して、配車できる状態に変更。 その後確定してもらって、自動配車状態へ移行させた。
B54: ="No"&ROW()-3 -> No51 | C54: 要望 | D54: 伊藤 | E54: 45793 | F54: 0.375 | G54: 0.66666667 | H54: 0.083333333 | I54: 45799 | J54: 45793 | K54: OA端末関連 | L54: 商品部 | N54: 成川 | O54: 低 | P54: 完了 | Q54: Google Cheromeの設定がデスクトップの時のものにそろえたい。 | R54: 完全に本人の要望のため協力はしたが自分で調査させて残りは本人に対応させる。
B55: ="No"&ROW()-3 -> No52 | C55: 課題 | D55: 伊藤 | E55: 45793 | F55: 0.45833333 | G55: 0.47916667 | H55: 0.020833333 | I55: 45793 | J55: 45793 | K55: 総務関連 | L55: 管理部 | N55: 坂田 | O55: 中 | P55: 完了 | Q55: コールセンター年間スケジュール登録による留守電のCTIへの設定の依頼調整。 | R55: 見積もり取得、登録スケジュールの伝達。スケジュールの確定。5/21 10：00 メール・電話対応。
B56: ="No"&ROW()-3 -> No53 | C56: 問合せ | D56: 佐々嶌 | E56: 45796 | F56: 0.67013889 | G56: 0.67708333 | H56: 0.0069444444 | I56: 45796 | K56: OA端末関連 | L56: 管理部 | N56: 上村 | O56: 低 | P56: 完了 | Q56: エクセルを開くとエラーが出ることがある。 閉じれば使えるが、対処方法があれば教えて欲しい。 | R56: https://qiita.com/misty299/items/07700bee14499222d814 「C:\Users\FMV\AppData\Local\Packages\Microsoft.AAD.BrokerPlugin_cw5n1h2txyewy」内のファイルを削除、MS365アカウントで再ログイン
B57: ="No"&ROW()-3 -> No54 | C57: 要望 | D57: 坂本 | E57: 45796 | F57: 0.41319444 | G57: 0.42013889 | H57: 0.0069444444 | I57: 45796 | J57: 45796 | K57: 業務運用 | L57: 顧客部 | N57: 久楽 | O57: 中 | P57: 完了 | Q57: 在庫品の出荷指示依頼 | R57: 在庫品の対応は手順不明のため、下村さんへ連絡。対応中に自動出荷指示がかかった。
B58: ="No"&ROW()-3 -> No55 | C58: 要望 | D58: 坂本 | E58: 45796 | F58: 0.45833333 | G58: 0.46527778 | H58: 0.0069444444 | I58: 45796 | J58: 45796 | K58: 業務運用 | L58: 営業管理部 | N58: 三縞 | O58: 中 | P58: 完了 | Q58: 混載設定追加 | R58: 既定手順で対応済
B59: ="No"&ROW()-3 -> No56 | C59: 要望 | D59: 坂本 | E59: 45798 | F59: 0.39583333 | G59: 0.41666667 | H59: 0.0069444444 | I59: 45798 | J59: 45798 | K59: 業務運用 | L59: 営業部 | N59: 佐藤 | O59: 中 | P59: 完了 | Q59: 出荷予定日変更 | R59: 既定手順で対応済
B60: ="No"&ROW()-3 -> No57 | C60: 要望 | D60: 坂本 | E60: 45798 | F60: 0.40625 | G60: 0.47916667 | H60: 0.0069444444 | I60: 45798 | J60: 45798 | K60: 業務運用 | L60: 営業管理部 | N60: 三縞 | O60: 中 | P60: 完了 | Q60: 混載設定追加 | R60: 既定手順で対応済
B61: ="No"&ROW()-3 -> No58 | C61: 要望 | D61: 坂本 | E61: 45798 | F61: 0.45833333 | G61: 0.46180556 | H61: 0.0034722222 | I61: 45791 | J61: 45791 | K61: 業務運用 | L61: 営業部 | N61: 見形 | O61: 中 | P61: 完了 | Q61: 直送品出荷指示 | R61: 既定手順で対応済
B62: ="No"&ROW()-3 -> No59 | C62: 課題 | D62: 伊藤 | E62: 45798 | F62: 0.72916667 | G62: 0.79166667 | H62: 0.0625 | I62: 45804 | K62: 業務運用 | L62: システム部 | O62: 高 | P62: 完了 | Q62: EDI端末のバックアップ制作。5/21HDDコピー。起動確認。LANアダプタ購入。 | R62: ひとまずコピー＆HDDの動作は確認。この後、PCを完全に予備用のものにして、LANアダプタの到着後に、サーバー室設置。福岡に引き渡してチェックをしてもらう予定。 →タスクスケジューラーの内容を改めて確認して、NWに接続してOKになってから。
B63: ="No"&ROW()-3 -> No60 | C63: 課題 | D63: 伊藤 | E63: 45799 | F63: 0.375 | K63: 業務運用 | L63: システム部 | O63: 高 | P63: 進行中 | Q63: USBメモリ他外部ストレージの運用の例外（役員・システム部・申請者用）の社内既定の作成。（加藤さん・磯辺さん確認中）
B64: ="No"&ROW()-3 -> No61 | C64: 課題 | D64: 伊藤 | E64: 45798 | F64: 0.41666667 | G64: 0.43055556 | H64: 0.013888889 | I64: 45798 | J64: 45798 | K64: 総務関連 | O64: 低 | P64: 完了 | Q64: LANケーブル、マウスなどのシステムに関わる備品のForestway での購入。 | R64: 既定手順で対応済
B65: ="No"&ROW()-3 -> No62 | C65: 要望 | D65: 坂本 | E65: 45799 | F65: 0.43402778 | G65: 0.44444444 | H65: 0.010416667 | I65: 45799 | J65: 45799 | K65: 業務運用 | L65: 顧客部 | N65: 池田 | O65: 中 | P65: 完了 | Q65: 在庫引き当て | R65: 既定手順で対応済
B66: ="No"&ROW()-3 -> No63 | C66: 要望 | D66: 坂本 | E66: 45799 | F66: 0.44444444 | G66: 0.44791667 | H66: 0.0034722222 | I66: 45799 | J66: 45799 | K66: 業務運用 | L66: 営業部 | N66: 佐藤 | O66: 中 | P66: 完了 | Q66: 出荷予定日変更 | R66: 既定手順で対応済
B67: ="No"&ROW()-3 -> No64 | C67: 要望 | D67: 坂本 | E67: 45800 | F67: 0.46875 | G67: 0.58333333 | H67: 0.020833333 | I67: 45800 | J67: 45800 | K67: OA端末関連 | L67: 顧客部 | N67: 村本 | O67: 中 | P67: 完了 | Q67: 端末起動時に毎回カーソルのみの画面表示となる | R67: グラフィックドライバとBIOSを更新した。依頼者不在のため様子見。
B68: ="No"&ROW()-3 -> No65 | C68: 要望 | D68: 坂本 | E68: 45800 | F68: 0.47916667 | G68: 0.48263889 | H68: 0.0034722222 | I68: 45800 | J68: 45800 | K68: 業務運用 | L68: 営業部 | N68: 佐藤 | O68: 中 | P68: 完了 | Q68: 出荷予定日変更 | R68: 既定手順で対応済
B69: ="No"&ROW()-3 -> No66 | C69: 要望 | D69: 坂本 | E69: 45800 | F69: 0.64583333 | G69: 0.65972222 | H69: 0.0069444444 | I69: 45800 | J69: 45800 | K69: 業務運用 | L69: 営業部 | N69: 佐藤 | O69: 高 | P69: 完了 | Q69: 出荷予定日変更（至急） | R69: 既定手順で対応済
B70: ="No"&ROW()-3 -> No67 | C70: 障害 | D70: 佐々嶌 坂本 伊藤 | E70: 45796 | F70: 0.60416667 | G70: 0.64583333 | H70: 0.041666667 | I70: 45796 | J70: 45796 | K70: 基幹端末関連 | L70: 顧客部 | N70: 齋藤 | O70: 中 | P70: 完了 | Q70: SCAWの得意先メモ表示で、管理番号入力後にEnterキーを押しても表示されない。他のアプリケーションや、SCAWの他の画面では正常に作動する。 | R70: KVM切替機の不具合。接続ケーブル挿抜により解消。
B71: ="No"&ROW()-3 -> No68 | C71: 要望 | D71: 坂本 | E71: 45804 | F71: 0.375 | G71: 0.41666667 | H71: 0.0625 | I71: 45804 | J71: 45805 | K71: その他 | L71: マーケティング部 | N71: 藤田 | O71: 低 | P71: 完了 | Q71: マーケティング部のBI分析でRを使用するが、Shiny(Rを利用したWebアプリパッケージ)の機能更新版が、一部動作しない。（analysis_1が起動しませんでした、というメッセージ） | R71: 分析ファイルの内容を、詳細ログが出力できるよう修正して、その結果をChatAIで分析。分析結果から更にコードを修正（タイムアウト値の調整、viewer関数の修正）して正常動作を確認。
B72: ="No"&ROW()-3 -> No69 | C72: 要望 | D72: 坂本 | E72: 45804 | F72: 0.39583333 | G72: 0.39930556 | H72: 0.0034722222 | I72: 45804 | J72: 45804 | K72: 業務運用 | L72: 顧客部 | N72: 木村 | O72: 中 | P72: 完了 | Q72: 直送品出荷指示 | R72: 既定手順で対応済
B73: ="No"&ROW()-3 -> No70 | C73: 課題 | D73: 坂本 | E73: 45804 | F73: 0.40625 | G73: 0.41319444 | H73: 0.0069444444 | I73: 45804 | J73: 45804 | K73: SCAW関連 | L73: 営業部 | N73: 見形 | O73: 中 | P73: 完了 | Q73: 売上伝票入力メニューで、確定日付を入力する際に権限不足のメッセージが表示されるので解消したい。対象は見形、佐藤の割当端末。 | R73: 下村さんに対応依頼
B74: ="No"&ROW()-3 -> No71 | C74: 障害 | D74: 坂本 | E74: 45804 | F74: 0.41666667 | G74: 0.58333333 | H74: 0.010416667 | I74: 45804 | J74: 45804 | K74: 基幹端末関連 | L74: 顧客部 | N74: 林田 | O74: 高 | P74: 完了 | Q74: 特定端末で、CTIシステムへのログインに失敗する。 | R74: 下村さんに確認依頼。本端末に割当された内線番号が、別の端末に割当されているため、ログイン不可。こちらの対応としては無し。
B75: ="No"&ROW()-3 -> No72 | C75: 要望 | D75: 坂本 | E75: 45804 | F75: 0.42708333 | G75: 0.43055556 | H75: 0.0034722222 | I75: 45804 | J75: 45804 | K75: OA端末関連 | L75: 管理部 | N75: 和田 | O75: 低 | P75: 完了 | Q75: 管理部の共有端末にリモートデスクトップしたいが、ユーザー/パスワードが不明 | R75: FMV/パスワード無しで接続可能であることを連絡
B76: ="No"&ROW()-3 -> No73 | C76: 課題 | D76: 坂本 | E76: 45804 | F76: 0.4375 | G76: 0.66666667 | H76: 0.020833333 | I76: 45804 | J76: 45804 | K76: OA端末関連 | L76: マーケティング部 | N76: 北山 | O76: 中 | P76: 完了 | Q76: Excelで数十万行を扱う際に、フリーズする（メモリ不足？）動作が見られる。相川さんの端末では問題なく動作する。 | R76: 北山さんPCと相川さんPCを比較すると、前者の方はWindows10でスペックも高い。取り急ぎOfficeの修復を実行して、経過観察とする。
... B93: ="No"&ROW()-3 -> No90 | C93: 問合せ | D93: 佐々嶌 坂本 | E93: 45810 | F93: 0.61458333 | G93: 0.66666667 | H93: 0.010416667 | I93: 45810 | J93: 45810 | K93: その他 | L93: 商品部 | N93: 安形 | O93: 低 | P93: 完了 | Q93: 5/31～6/1の未引当メールが無いが、妥当か（情報取得や配信処理の不具合ではないか） | R93: システム定例会議で報告。メール発報基準に満たないと考えられるため、配信されないのは正常動作
B94: ="No"&ROW()-3 -> No91 | C94: 要望 | D94: 佐々嶌 | E94: 45813 | F94: 0.40277778 | G94: 0.40625 | H94: 0.0034722222 | J94: 45813 | K94: 業務運用 | L94: 顧客部 | N94: 岡崎 | O94: 中 | P94: 完了 | Q94: 直送品出荷指示 | R94: 既定手順で対応済
B95: ="No"&ROW()-3 -> No92 | C95: 要望 | D95: 坂本 | E95: 45810 | F95: 0.375 | G95: 0.38194444 | H95: 0.0069444444 | I95: 45810 | J95: 45810 | K95: OA端末関連 | L95: 営業管理部 | N95: 小幡 | O95: 低 | P95: 完了 | Q95: セキュリティソフトのAvast!が無料ライセンス期限の通知画面が表示される | R95: 社内標準で使用しているセキュリティソフトではないため、アンインストールを実施
B96: ="No"&ROW()-3 -> No93 | C96: 障害 | D96: 佐々嶌 坂本 伊藤 | E96: 45810 | F96: 0.4125 | G96: 0.4375 | H96: 0.025 | K96: サーバー | L96: 全体 | N96: 北澤 | O96: 高 | P96: 完了 | Q96: SCAW画面が固まって動かないと連絡あり。 | R96: 下村さんに電話。 SCAWDBサービスが落ちてしまっていた模様。 Forestway、ココデカウも接続不可。物流にも影響あり。 DBサーバーを再起動して復旧。 原因はオラクル統計情報を取得するテーブルの表領域が枯渇していた為？
B97: ="No"&ROW()-3 -> No94 | C97: 要望 | D97: 伊藤 | E97: 45811 | F97: 0.54166667 | G97: 0.55902778 | H97: 0.017361111 | I97: 45811 | J97: 45811 | K97: SCAW関連 | L97: 川口配送センター | N97: 高橋 | O97: 低 | P97: 完了 | Q97: SCAWメニュー申請 小林、足達、高山 | R97: 所定の手順で対応し終了。ワークフロー、社内メールで伝達。
B98: ="No"&ROW()-3 -> No95 | C98: 要望 | D98: 坂本 | E98: 45810 | F98: 0.54166667 | G98: 0.55902778 | H98: 0.0069444444 | I98: 45810 | J98: 45810 | K98: 業務運用 | L98: 営業管理部 | N98: 田中 | O98: 中 | P98: 完了 | Q98: 仕入先登録 | R98: 既定手順で対応済
B99: ="No"&ROW()-3 -> No96 | C99: 障害 | D99: 佐々嶌 | E99: 45810 | F99: 0.44444444 | G99: 0.46527778 | H99: 0.020833333 | J99: 45810 | K99: 配送 | L99: 川口配送センター | N99: 中澤 | O99: 低 | P99: 完了 | Q99: 配送リスト（インプロ）が表示されなくなってしまった。 | R99: プリンター設定がおかしくなっていたので正しく設定することで対応できた。7/4（金）再発。通常使用するプリンタをコニカミノルタにしてScawを再起動して対応。浅見PCの共有が邪魔してる可能性があり共有ドライバ削除。再発しないか確認を継続してもらう。
B100: ="No"&ROW()-3 -> No97 | C100: 障害 | D100: 坂本 | E100: 45812 | F100: 0.40277778 | G100: 0.45833333 | H100: 0.055555556 | I100: 45812 | J100: 45812 | K100: OA端末関連 | L100: 営業部 | N100: 長谷川 | O100: 高 | P100: 完了 | Q100: OA端末(ノートPC)から外部ディスプレイに表示されない | R100: マウス、キーボードは切替機を通して正常に動作する。映像出力のみ問題が起こるが、何故か基幹PCからの映像出力は問題がない。モニター自体を交換して解消。
B101: ="No"&ROW()-3 -> No98 | C101: 問合せ | D101: 坂本 | E101: 45811 | F101: 0.54166667 | G101: 0.55555556 | H101: 0.013888889 | I101: 45811 | J101: 45811 | K101: その他 | L101: マーケティング部 | N101: 樋口 | O101: 中 | P101: 完了 | Q101: 広告配信で配信対象の顧客を識別するための個人情報を配信業者へ渡す際、データのハッシュ化についての確認 | R101: ハッシュ化について説明。合わせてハッシュ化された個人情報でも、アルゴリズムが分かれば個人特定につながるため、利用保留とした方がよい旨を連絡。
B102: ="No"&ROW()-3 -> No99 | C102: 要望 | D102: 坂本 | E102: 45811 | F102: 0.46875 | G102: 0.55902778 | H102: 0.0069444444 | I102: 45811 | J102: 45811 | K102: 業務運用 | L102: 顧客部 | N102: 見形 | O102: 中 | P102: 完了 | Q102: 出荷予定日変更 | R102: 既定手順で対応済
B103: ="No"&ROW()-3 -> No100 | C103: 要望 | D103: 坂本 | E103: 45811 | F103: 0.40277778 | G103: 0.47916667 | H103: 0.010416667 | I103: 45811 | J103: 45811 | K103: 業務運用 | L103: 営業管理部 | N103: 三縞 | O103: 中 | P103: 完了 | Q103: 混載設定追加 | R103: 既定手順で対応済
B104: ="No"&ROW()-3 -> No101 | C104: 障害 | D104: 坂本 | E104: 45810 | F104: 0.4375 | G104: 0.45833333 | H104: 0.010416667 | I104: 45810 | J104: 45810 | K104: 名刺 | L104: 顧客部 | N104: 村本 | O104: 中 | P104: 完了 | Q104: 名刺編集の「コピーして新規作成」処理が実行不可 | R104: 下村さんにエスカレーション。基幹DB障害発生検知後から10:40頃まで、FWS3⇒基幹へアクセスしないよう設定変更していた影響とのこと。
B105: ="No"&ROW()-3 -> No102 | C105: 要望 | D105: 伊藤 | E105: 45811 | F105: 0.55902778 | G105: 0.56597222 | H105: 0.0069444444 | I105: 45811 | J105: 45811 | K105: SCAW関連 | L105: 顧客部 | N105: 村本 | O105: 低 | P105: 完了 | Q105: SCAW使用者登録申請 大井 | R105: 所定の手順で対応し終了。ワークフロー、社内メールで伝達。
B106: ="No"&ROW()-3 -> No103 | C106: 障害 | D106: 坂本 | E106: 45812 | F106: 0.66666667 | G106: 0.6875 | H106: 0.020833333 | I106: 45812 | J106: 45812 | K106: 名刺 | L106: 顧客部 | N106: 村本 | O106: 中 | P106: 完了 | Q106: AdobeILでログイン認証が要求される | R106: 管理台帳を基に再ログイン。アカウントロックされたのかパスワードがリセットされたため再発行した。
B107: ="No"&ROW()-3 -> No104 | C107: 要望 | D107: 坂本 | E107: 45810 | F107: 0.58333333 | G107: 0.59722222 | H107: 0.013888889 | I107: 45810 | J107: 45810 | K107: 業務運用 | L107: 顧客部 | N107: 矢ヶ崎 | O107: 中 | P107: 完了 | Q107: 在庫引き当て | R107: 既定手順で対応済
B108: ="No"&ROW()-3 -> No105 | C108: 課題 | D108: 佐々嶌 | E108: 45809 | F108: 0.375 | G108: 0.75 | H108: 0.33333333 | I108: 45809 | J108: 45809 | K108: 業務運用 | L108: 顧客部 | O108: 中 | P108: 完了 | Q108: 停電時に稼働していてほしいPC端末がUPSに接続されていない。 | R108: UPSがどのエリアに接続されているか確認。電源タップの接続のやり直しと、起動の確認作業を実施。
B109: ="No"&ROW()-3 -> No106 | C109: 課題 | D109: 坂本 | E109: 45809 | F109: 0.375 | G109: 0.75 | H109: 0.33333333 | I109: 45809 | J109: 45809 | K109: 業務運用 | L109: 顧客部 | O109: 中 | P109: 完了 | Q109: 停電時に稼働していてほしいPC端末がUPSに接続されていない。 | R109: UPSがどのエリアに接続されているか確認。電源タップの接続のやり直しと、起動の確認作業を実施。
B110: ="No"&ROW()-3 -> No107 | C110: 課題 | D110: 伊藤 | E110: 45809 | F110: 0.375 | G110: 0.75 | H110: 0.33333333 | I110: 45809 | J110: 45809 | K110: 業務運用 | L110: 顧客部 | O110: 中 | P110: 完了 | Q110: 停電時に稼働していてほしいPC端末がUPSに接続されていない。 | R110: UPSがどのエリアに接続されているか確認。電源タップの接続のやり直しと、起動の確認作業を実施。
B111: ="No"&ROW()-3 -> No108 | C111: 障害 | D111: 伊藤 | E111: 45810 | F111: 0.625 | G111: 0.63888889 | H111: 0.013888889 | I111: 45810 | J111: 45810 | K111: ネットワーク | L111: システム部 | O111: 中 | P111: 完了 | Q111: データプラス 伊藤様から電話があり、Hubの電源ケーブル破損。代わりの準備の依頼。 | R111: 社内で規格の合うものを確認し佐川で発送。
B112: ="No"&ROW()-3 -> No109 | C112: 支援 | D112: 伊藤 | E112: 45811 | F112: 0.45833333 | G112: 0.47569444 | H112: 0.017361111 | I112: 45811 | J112: 45811 | K112: OA端末関連 | L112: 全体 | O112: 低 | P112: 完了 | Q112: ローカルチャットAIの試用版を使用しているユーザーへの有料版使用への 喚起メール送信。 | R112: 確認方法を記載した社内メールを全社員に送信。
B113: ="No"&ROW()-3 -> No110 | C113: 要望 | D113: 伊藤 | E113: 45811 | F113: 0.75 | G113: 0.83333333 | H113: 0.083333333 | I113: 45811 | J113: 45811 | K113: OA端末関連 | L113: 川口配送センター | N113: 浅見 | O113: 低 | P113: 完了 | Q113: OA側複合機 スキャンフォルダを追加したい。 | R113: PC側、複合機ともに設定をマニュアル通り設定た。PCから複合機のフォルダが見えているのに複合機本体のパネルから見えない。調査のため一度終了。
B114: ="No"&ROW()-3 -> No111 | C114: 要望 | D114: 伊藤 | E114: 45813 | F114: 0.45833333 | G114: 0.5 | H114: 0.041666667 | I114: 45813 | J114: 45813 | K114: OA端末関連 | L114: 川口配送センター | N114: 浅見 | O114: 低 | P114: 完了 | Q114: OA側複合機 スキャンフォルダを追加したい。 | R114: やはり作成したものは見えず。元からあったフォルダが見えているから、それをそのまま流用してもらい完了。
B115: ="No"&ROW()-3 -> No112 | C115: 要望 | D115: 坂本 | E115: 45814 | F115: 0.44791667 | G115: 0.45486111 | H115: 0.0069444444 | I115: 45814 | J115: 45814 | K115: OA端末関連 | L115: 顧客部 | N115: 池田 | O115: 低 | P115: 完了 | Q115: pdfファイルを開くとedgeが起動し、内容も表示されない | R115: pdfファイルをAdobe Acrobatに関連付けして開き、内容が表示されることを確認
B116: ="No"&ROW()-3 -> No113 | C116: 障害 | D116: 坂本 | E116: 45812 | F116: 0.70833333 | G116: 0.71875 | H116: 0.010416667 | I116: 45812 | J116: 45812 | K116: 名刺 | L116: 顧客部 | N116: 村本 | O116: 中 | P116: 完了 | Q116: 名刺編集画面で緊急コールの表示 | R116: 村本さんへ福岡システム部へエスカレーションするよう連携
B117: ="No"&ROW()-3 -> No114 | C117: 要望 | D117: 坂本 | E117: 45812 | F117: 0.38541667 | G117: 0.38888889 | H117: 0.0034722222 | I117: 45812 | J117: 45812 | K117: 業務運用 | L117: 営業部 | N117: 見形 | O117: 中 | P117: 完了 | Q117: 直送品出荷指示 | R117: 既定手順で対応済
B118: ="No"&ROW()-3 -> No115 | C118: 障害 | D118: 坂本 | E118: 45812 | F118: 0.60416667 | G118: 0.625 | H118: 0.020833333 | I118: 45812 | J118: 45812 | K118: OA端末関連 | L118: 商品部 | N118: 須永 | O118: 中 | P118: 完了 | Q118: OA端末のディスク空き容量が不足している、どう対処したらよいか。 | R118: ローカルに必要なファイルはドキュメントフォルダに集約したとのことで、システムフォルダを除きサイズが大きいファイルを表示するバッチプログラムを提供し、削除候補として検討するよう依頼。
B119: ="No"&ROW()-3 -> No116 | C119: 障害 | D119: 坂本 | E119: 45812 | F119: 0.625 | G119: 0.63194444 | H119: 0.0069444444 | I119: 45812 | J119: 45812 | K119: 業務運用 | L119: 顧客部 | N119: 野尻 | O119: 中 | P119: 完了 | Q119: 在庫引き当て | R119: 既定手順で対応済
B120: ="No"&ROW()-3 -> No117 | C120: 支援 | D120: 坂本 | E120: 45814 | F120: 0.58333333 | G120: 0.60416667 | H120: 0.020833333 | I120: 45814 | J120: 45814 | K120: 業務運用 | L120: 営業管理部 | N120: 小幡 | O120: 中 | P120: 完了 | Q120: VD一括登録 | R120: 既定手順で対応済
B121: ="No"&ROW()-3 -> No118 | C121: 要望 | D121: 伊藤 | E121: 45814 | F121: 0.39583333 | G121: 0.39583333 | H121: 0.020833333 | I121: 45814 | J121: 45814 | K121: 総務関連 | L121: 営業部 | N121: 森山 | O121: 中 | P121: 完了 | Q121: 西日本 森山さん EDION支給のガラケーからスマホに機種変更したいという要望。 | R121: EDION携帯電話をフォーレストの携帯電話として機種変はできない。（ナンバーポータビリティも不可）となるので新規の番号でiPhone、Androidで契約の見積もりを依頼。
B122: ="No"&ROW()-3 -> No119 | C122: 要望 | D122: 伊藤 | E122: 45814 | F122: 0.45833333 | G122: 0.47916667 | H122: 0.020833333 | I122: 45814 | J122: 45814 | K122: 総務関連 | L122: システム部 | N122: 坂本 | O122: 低 | P122: 完了 | Q122: 本社でモニターが破損のため、坂本さんのモニターを譲渡。在庫がなく今後の対応用に購入予定。 | R122: ダイワボウ一瀬様にメールで見積もり要請。3台分。
B123: ="No"&ROW()-3 -> No120 | C123: 要望 | D123: 伊藤 | E123: 45814 | F123: 0.54166667 | G123: 0.5625 | H123: 0.020833333 | I123: 45814 | J123: 45814 | K123: 基幹端末関連 | L123: 物流部 | N123: 山中 | O123: 低 | P123: 完了 | Q123: 基幹にインクジェットプリンターを接続したいのでLANケーブルとリモートでの設定をしてほしい。 | R123: LANケーブルを送ったが長さが足りない。より長いものを送る。6/9に設定の予定。
B124: ="No"&ROW()-3 -> No121 | C124: 要望 | D124: 伊藤 | E124: 45814 | F124: 0.66666667 | G124: 0.6875 | H124: 0.020833333 | I124: 45814 | J124: 45814 | K124: OA端末関連 | L124: 顧客部 | N124: 林田 | O124: 低 | P124: 完了 | Q124: PowerPointを使用したい。 | R124: Office2019から365に入れ替え。動作確認
... B130: ="No"&ROW()-3 -> No127 | C130: 問合せ | D130: 伊藤 | E130: 45817 | F130: 0.6875 | G130: 0.69791667 | H130: 0.010416667 | I130: 45817 | J130: 45817 | K130: ネットワーク | L130: その他 | N130: 岡崎 | O130: 低 | P130: 完了 | Q130: データプラス 伊藤様から先日設定したルーターの情報を聞きたいと電話連絡があり対応。 | R130: NTT東日本 荒木様とメールで確認。伊藤様に共有。
B131: ="No"&ROW()-3 -> No128 | C131: 要望 | D131: 伊藤 | E131: 45818 | F131: 0.39583333 | G131: 0.4375 | H131: 0.041666667 | I131: 45825 | K131: OA端末関連 | L131: 顧客部 | N131: 岡本 | O131: 低 | P131: 完了 | Q131: 採用を予定していて、以前申請のあった中断中の端末の準備を再開してほしいとのこと。 | R131: キッティング作業。
B132: ="No"&ROW()-3 -> No129 | C132: 課題 | D132: 伊藤 | E132: 45818 | F132: 0.41666667 | G132: 0.58333333 | H132: 0.16666667 | I132: 45818 | J132: 45818 | K132: OA端末関連 | L132: 全体 | O132: 中 | P132: 完了 | Q132: Windows updateで通信が遅くなる。 | R132: Windows updateに関しての対策を検証。事前通知、Skyで更新時期の変更ができるかの対策を検証。
B133: ="No"&ROW()-3 -> No130 | C133: 要望 | D133: 伊藤 | E133: 45818 | I133: 45825 | K133: 基幹端末関連 | L133: 顧客部 | N133: 岡本 | O133: 低 | P133: 完了 | Q133: 採用を予定していて、以前申請のあった中断中の端末の準備を再開してほしいとのこと。 | R133: キッティング作業。
B134: ="No"&ROW()-3 -> No131 | C134: 課題 | D134: 伊藤 | E134: 45819 | F134: 0.41666667 | G134: 0.70833333 | H134: 0.125 | I134: 45819 | J134: 45819 | K134: OA端末関連 | L134: 全体 | O134: 中 | P134: 完了 | Q134: skyで設定変更を全OA端末に反映できない。 | R134: ESETにskyによるバックグラウンド実行でバッチ処理ができないので、マニュアルを作成し、個別対応の依頼。
B135: ="No"&ROW()-3 -> No132 | C135: 要望 | D135: 伊藤 | E135: 45819 | F135: 0.54166667 | G135: 0.58333333 | H135: 0.041666667 | I135: 45819 | J135: 45819 | K135: 総務関連 | L135: システム部 | O135: 低 | P135: 完了 | Q135: PCモニター故障。在庫がなくなったので購入へ。 | R135: 見積もり、稟議書作成、稟議申請、ダイワボウに発注。
B136: ="No"&ROW()-3 -> No133 | C136: 課題 | D136: 伊藤 | E136: 45820 | F136: 0.41666667 | G136: 0.45833333 | H136: 0.041666667 | I136: 45820 | J136: 45820 | K136: OA端末関連 | L136: 全体 | O136: 中 | P136: 完了 | Q136: ESETで一部の端末に設定が事前にされている場合と管理者権限を求められて設定できない。 | R136: マニュアルを改編。共用端末に関しては連絡し一時保留。
B137: ="No"&ROW()-3 -> No134 | C137: 要望 | D137: 佐々嶌 | E137: 45819 | F137: 0.39930556 | G137: 0.40277778 | H137: 0.0034722222 | I137: 45819 | J137: 45819 | K137: 業務運用 | L137: 顧客部 | N137: 岡崎 | O137: 中 | P137: 完了 | Q137: 直送品出荷指示 | R137: 既定手順で対応済
B138: ="No"&ROW()-3 -> No135 | C138: 要望 | D138: 坂本 | E138: 45819 | F138: 0.45833333 | G138: 0.5 | H138: 0.020833333 | I138: 45819 | J138: 45819 | K138: 業務運用 | L138: 営業管理部 | N138: 三縞 | O138: 中 | P138: 完了 | Q138: 混載設定の削除、追加 | R138: 削除対応は下村さんに確認して実施
B139: ="No"&ROW()-3 -> No136 | C139: 要望 | D139: 坂本 | E139: 45819 | F139: 0.69791667 | G139: 0.40277778 | H139: 0.041666667 | I139: 45819 | J139: 45819 | K139: 業務運用 | L139: 営業部 | N139: 見形 | O139: 中 | P139: 完了 | Q139: 出荷予定日・着日変更 | R139: 既定手順で対応済
B140: ="No"&ROW()-3 -> No137 | C140: 要望 | D140: 坂本 | E140: 45820 | F140: 0.45833333 | G140: 0.46527778 | H140: 0.0069444444 | I140: 45820 | J140: 45820 | K140: 業務運用 | L140: 管理部 | N140: 和田 | O140: 中 | P140: 完了 | Q140: 請求先変更 | R140: 既定手順で対応済
B141: ="No"&ROW()-3 -> No138 | C141: 要望 | D141: 坂本 | E141: 45820 | F141: 0.63888889 | G141: 0.66666667 | H141: 0.027777778 | I141: 45820 | J141: 45820 | K141: 業務運用 | L141: 営業管理部 | N141: 野崎 | O141: 中 | P141: 完了 | Q141: VD設定 | R141: 既定手順で対応済
B142: ="No"&ROW()-3 -> No139 | C142: 要望 | D142: 坂本 | E142: 45820 | F142: 0.83333333 | G142: 0.38541667 | H142: 0.020833333 | I142: 45821 | J142: 45821 | K142: 業務運用 | L142: 営業管理部 | N142: 野崎 | O142: 中 | P142: 完了 | Q142: VD設定 | R142: 既定手順で対応済
B143: ="No"&ROW()-3 -> No140 | C143: 要望 | D143: 坂本 | E143: 45821 | F143: 0.41666667 | G143: 0.42361111 | H143: 0.0069444444 | I143: 45821 | J143: 45821 | K143: 業務運用 | L143: 営業部 | N143: 佐藤 | O143: 中 | P143: 完了 | Q143: 出荷予定日変更 | R143: 既定手順で対応済
B144: ="No"&ROW()-3 -> No141 | C144: 要望 | D144: 坂本 | E144: 45821 | F144: 0.46180556 | G144: 0.48263889 | H144: 0.0069444444 | I144: 45821 | J144: 45821 | K144: 業務運用 | L144: 営業部 | N144: 佐藤 | O144: 中 | P144: 完了 | Q144: 出荷予定日変更 | R144: 既定手順で対応済
B145: ="No"&ROW()-3 -> No142 | C145: 要望 | D145: 坂本 | E145: 45821 | F145: 0.52083333 | G145: 0.75694444 | H145: 0.020833333 | I145: 45821 | J145: 45821 | K145: 業務運用 | L145: 営業管理部 | N145: 野崎 | O145: 中 | P145: 完了 | Q145: VD設定 | R145: 既定手順で対応済
B146: ="No"&ROW()-3 -> No143 | C146: 要望 | D146: 坂本 | E146: 45825 | F146: 0.38194444 | G146: 0.38888889 | H146: 0.0069444444 | I146: 45825 | J146: 45825 | K146: 業務運用 | L146: 営業部 | N146: 見形 | O146: 中 | P146: 完了 | Q146: 直送品出荷指示 | R146: 既定手順で対応済
...

Sheet 祝日シート
A1: 45517
A2: 45518
A3: 45519
A4: 45656
A5: 45657
A6: 45658
A7: 45659
A8: 45660
A9: 45882
A10: 45883
A11: 45884
A12: 46021
... A24: 46390
